{
    "breadcrumbData": {
        "isVirtualManuscript": false,
        "primaryManuscript": {
            "collection": {
                "label": "St. Gallen, Stiftsbibliothek",
                "url": "https://www.e-codices.unifr.ch/en/search/?iCurrentPage=1&sQueryString=&sSearchField=fullText&sSortField=score&aSelectedFacets[collection_facet][]=St.+Gallen%2C+Stiftsbibliothek"
            },
            "shelfmark": {
                "label": "Cod. Sang. 246",
                "url": "https://www.e-codices.unifr.ch/en/list/one/csg/0246"
            },
            "title": {
                "label": "Rupertus Tuitiensis, Liber de divinis officiis"
            },
            "page": {
                "label": "Thumbnails"
            }
        }
    },
    "canvases": [
        {
            "id": "155693",
            "src": "https://www.e-codices.unifr.ch/loris/csg/csg-0246/csg-0246_e001.jp2/full/,150/0/default/jpg",
            "href": "https://www.e-codices.unifr.ch/en/csg/0246/bindingA",
            "width": 112.5,
            "height": 150,
            "label": "Front cover",
            "active": true
        },
        {
            "id": "155697",
            "src": "https://www.e-codices.unifr.ch/loris/csg/csg-0246/csg-0246_e005.jp2/full/,150/0/default/jpg",
            "href": "https://www.e-codices.unifr.ch/en/csg/0246/bindingE",
            "width": 112.5,
            "height": 150,
            "label": "Front paste-down"
        },
        {
            "id": "155465",
            "src": "https://www.e-codices.unifr.ch/loris/csg/csg-0246/csg-0246_001.jp2/full/,150/0/default/jpg",
            "href": "https://www.e-codices.unifr.ch/en/csg/0246/1",
            "width": 112.5,
            "height": 150,
            "label": "p. 1"
        },
        {
            "id": "155466",
            "src": "https://www.e-codices.unifr.ch/loris/csg/csg-0246/csg-0246_002.jp2/full/,150/0/default/jpg",
            "href": "https://www.e-codices.unifr.ch/en/csg/0246/2",
            "width": 112.5,
            "height": 150,
            "label": "p. 2"
        },
        {
            "id": "155467",
            "src": "https://www.e-codices.unifr.ch/loris/csg/csg-0246/csg-0246_003.jp2/full/,150/0/default/jpg",
            "href": "https://www.e-codices.unifr.ch/en/csg/0246/3",
            "width": 112.5,
            "height": 150,
            "label": "p. 3"
        },
        {
            "id": "155468",
            "src": "https://www.e-codices.unifr.ch/loris/csg/csg-0246/csg-0246_004.jp2/full/,150/0/default/jpg",
            "href": "https://www.e-codices.unifr.ch/en/csg/0246/4",
            "width": 112.5,
            "height": 150,
            "label": "p. 4"
        },
        {
            "id": "155469",
            "src": "https://www.e-codices.unifr.ch/loris/csg/csg-0246/csg-0246_005.jp2/full/,150/0/default/jpg",
            "href": "https://www.e-codices.unifr.ch/en/csg/0246/5",
            "width": 112.5,
            "height": 150,
            "label": "p. 5"
        },
        {
            "id": "155470",
            "src": "https://www.e-codices.unifr.ch/loris/csg/csg-0246/csg-0246_006.jp2/full/,150/0/default/jpg",
            "href": "https://www.e-codices.unifr.ch/en/csg/0246/6",
            "width": 112.5,
            "height": 150,
            "label": "p. 6"
        },
        {
            "id": "155471",
            "src": "https://www.e-codices.unifr.ch/loris/csg/csg-0246/csg-0246_007.jp2/full/,150/0/default/jpg",
            "href": "https://www.e-codices.unifr.ch/en/csg/0246/7",
            "width": 112.5,
            "height": 150,
            "label": "p. 7"
        },
        {
            "id": "155472",
            "src": "https://www.e-codices.unifr.ch/loris/csg/csg-0246/csg-0246_008.jp2/full/,150/0/default/jpg",
            "href": "https://www.e-codices.unifr.ch/en/csg/0246/8",
            "width": 112.5,
            "height": 150,
            "label": "p. 8"
        },
        {
            "id": "155473",
            "src": "https://www.e-codices.unifr.ch/loris/csg/csg-0246/csg-0246_009.jp2/full/,150/0/default/jpg",
            "href": "https://www.e-codices.unifr.ch/en/csg/0246/9",
            "width": 112.5,
            "height": 150,
            "label": "p. 9"
        },
        {
            "id": "155474",
            "src": "https://www.e-codices.unifr.ch/loris/csg/csg-0246/csg-0246_010.jp2/full/,150/0/default/jpg",
            "href": "https://www.e-codices.unifr.ch/en/csg/0246/10",
            "width": 112.5,
            "height": 150,
            "label": "p. 10"
        },
        {
            "id": "155475",
            "src": "https://www.e-codices.unifr.ch/loris/csg/csg-0246/csg-0246_011.jp2/full/,150/0/default/jpg",
            "href": "https://www.e-codices.unifr.ch/en/csg/0246/11",
            "width": 112.5,
            "height": 150,
            "label": "p. 11"
        },
        {
            "id": "155476",
            "src": "https://www.e-codices.unifr.ch/loris/csg/csg-0246/csg-0246_012.jp2/full/,150/0/default/jpg",
            "href": "https://www.e-codices.unifr.ch/en/csg/0246/12",
            "width": 112.5,
            "height": 150,
            "label": "p. 12"
        },
        {
            "id": "155477",
            "src": "https://www.e-codices.unifr.ch/loris/csg/csg-0246/csg-0246_013.jp2/full/,150/0/default/jpg",
            "href": "https://www.e-codices.unifr.ch/en/csg/0246/13",
            "width": 112.5,
            "height": 150,
            "label": "p. 13"
        },
        {
            "id": "155478",
            "src": "https://www.e-codices.unifr.ch/loris/csg/csg-0246/csg-0246_014.jp2/full/,150/0/default/jpg",
            "href": "https://www.e-codices.unifr.ch/en/csg/0246/14",
            "width": 112.5,
            "height": 150,
            "label": "p. 14"
        },
        {
            "id": "155479",
            "src": "https://www.e-codices.unifr.ch/loris/csg/csg-0246/csg-0246_015.jp2/full/,150/0/default/jpg",
            "href": "https://www.e-codices.unifr.ch/en/csg/0246/15",
            "width": 112.5,
            "height": 150,
            "label": "p. 15"
        },
        {
            "id": "155480",
            "src": "https://www.e-codices.unifr.ch/loris/csg/csg-0246/csg-0246_016.jp2/full/,150/0/default/jpg",
            "href": "https://www.e-codices.unifr.ch/en/csg/0246/16",
            "width": 112.5,
            "height": 150,
            "label": "p. 16"
        },
        {
            "id": "155481",
            "src": "https://www.e-codices.unifr.ch/loris/csg/csg-0246/csg-0246_017.jp2/full/,150/0/default/jpg",
            "href": "https://www.e-codices.unifr.ch/en/csg/0246/17",
            "width": 112.5,
            "height": 150,
            "label": "p. 17"
        },
        {
            "id": "155482",
            "src": "https://www.e-codices.unifr.ch/loris/csg/csg-0246/csg-0246_018.jp2/full/,150/0/default/jpg",
            "href": "https://www.e-codices.unifr.ch/en/csg/0246/18",
            "width": 112.5,
            "height": 150,
            "label": "p. 18"
        },
        {
            "id": "155483",
            "src": "https://www.e-codices.unifr.ch/loris/csg/csg-0246/csg-0246_019.jp2/full/,150/0/default/jpg",
            "href": "https://www.e-codices.unifr.ch/en/csg/0246/19",
            "width": 112.5,
            "height": 150,
            "label": "p. 19"
        },
        {
            "id": "155484",
            "src": "https://www.e-codices.unifr.ch/loris/csg/csg-0246/csg-0246_020.jp2/full/,150/0/default/jpg",
            "href": "https://www.e-codices.unifr.ch/en/csg/0246/20",
            "width": 112.5,
            "height": 150,
            "label": "p. 20"
        },
        {
            "id": "155485",
            "src": "https://www.e-codices.unifr.ch/loris/csg/csg-0246/csg-0246_021.jp2/full/,150/0/default/jpg",
            "href": "https://www.e-codices.unifr.ch/en/csg/0246/21",
            "width": 112.5,
            "height": 150,
            "label": "p. 21"
        },
        {
            "id": "155486",
            "src": "https://www.e-codices.unifr.ch/loris/csg/csg-0246/csg-0246_022.jp2/full/,150/0/default/jpg",
            "href": "https://www.e-codices.unifr.ch/en/csg/0246/22",
            "width": 112.5,
            "height": 150,
            "label": "p. 22"
        },
        {
            "id": "155487",
            "src": "https://www.e-codices.unifr.ch/loris/csg/csg-0246/csg-0246_023.jp2/full/,150/0/default/jpg",
            "href": "https://www.e-codices.unifr.ch/en/csg/0246/23",
            "width": 112.5,
            "height": 150,
            "label": "p. 23"
        },
        {
            "id": "155488",
            "src": "https://www.e-codices.unifr.ch/loris/csg/csg-0246/csg-0246_024.jp2/full/,150/0/default/jpg",
            "href": "https://www.e-codices.unifr.ch/en/csg/0246/24",
            "width": 112.5,
            "height": 150,
            "label": "p. 24"
        },
        {
            "id": "155489",
            "src": "https://www.e-codices.unifr.ch/loris/csg/csg-0246/csg-0246_025.jp2/full/,150/0/default/jpg",
            "href": "https://www.e-codices.unifr.ch/en/csg/0246/25",
            "width": 112.5,
            "height": 150,
            "label": "p. 25"
        },
        {
            "id": "155490",
            "src": "https://www.e-codices.unifr.ch/loris/csg/csg-0246/csg-0246_026.jp2/full/,150/0/default/jpg",
            "href": "https://www.e-codices.unifr.ch/en/csg/0246/26",
            "width": 112.5,
            "height": 150,
            "label": "p. 26"
        },
        {
            "id": "155491",
            "src": "https://www.e-codices.unifr.ch/loris/csg/csg-0246/csg-0246_027.jp2/full/,150/0/default/jpg",
            "href": "https://www.e-codices.unifr.ch/en/csg/0246/27",
            "width": 112.5,
            "height": 150,
            "label": "p. 27"
        },
        {
            "id": "155492",
            "src": "https://www.e-codices.unifr.ch/loris/csg/csg-0246/csg-0246_028.jp2/full/,150/0/default/jpg",
            "href": "https://www.e-codices.unifr.ch/en/csg/0246/28",
            "width": 112.5,
            "height": 150,
            "label": "p. 28"
        },
        {
            "id": "155493",
            "src": "https://www.e-codices.unifr.ch/loris/csg/csg-0246/csg-0246_029.jp2/full/,150/0/default/jpg",
            "href": "https://www.e-codices.unifr.ch/en/csg/0246/29",
            "width": 112.5,
            "height": 150,
            "label": "p. 29"
        },
        {
            "id": "155494",
            "src": "https://www.e-codices.unifr.ch/loris/csg/csg-0246/csg-0246_030.jp2/full/,150/0/default/jpg",
            "href": "https://www.e-codices.unifr.ch/en/csg/0246/30",
            "width": 112.5,
            "height": 150,
            "label": "p. 30"
        },
        {
            "id": "155495",
            "src": "https://www.e-codices.unifr.ch/loris/csg/csg-0246/csg-0246_031.jp2/full/,150/0/default/jpg",
            "href": "https://www.e-codices.unifr.ch/en/csg/0246/31",
            "width": 112.5,
            "height": 150,
            "label": "p. 31"
        },
        {
            "id": "155496",
            "src": "https://www.e-codices.unifr.ch/loris/csg/csg-0246/csg-0246_032.jp2/full/,150/0/default/jpg",
            "href": "https://www.e-codices.unifr.ch/en/csg/0246/32",
            "width": 112.5,
            "height": 150,
            "label": "p. 32"
        },
        {
            "id": "155497",
            "src": "https://www.e-codices.unifr.ch/loris/csg/csg-0246/csg-0246_033.jp2/full/,150/0/default/jpg",
            "href": "https://www.e-codices.unifr.ch/en/csg/0246/33",
            "width": 112.5,
            "height": 150,
            "label": "p. 33"
        },
        {
            "id": "155498",
            "src": "https://www.e-codices.unifr.ch/loris/csg/csg-0246/csg-0246_034.jp2/full/,150/0/default/jpg",
            "href": "https://www.e-codices.unifr.ch/en/csg/0246/34",
            "width": 112.5,
            "height": 150,
            "label": "p. 34"
        },
        {
            "id": "155499",
            "src": "https://www.e-codices.unifr.ch/loris/csg/csg-0246/csg-0246_035.jp2/full/,150/0/default/jpg",
            "href": "https://www.e-codices.unifr.ch/en/csg/0246/35",
            "width": 112.5,
            "height": 150,
            "label": "p. 35"
        },
        {
            "id": "155500",
            "src": "https://www.e-codices.unifr.ch/loris/csg/csg-0246/csg-0246_036.jp2/full/,150/0/default/jpg",
            "href": "https://www.e-codices.unifr.ch/en/csg/0246/36",
            "width": 112.5,
            "height": 150,
            "label": "p. 36"
        },
        {
            "id": "155501",
            "src": "https://www.e-codices.unifr.ch/loris/csg/csg-0246/csg-0246_037.jp2/full/,150/0/default/jpg",
            "href": "https://www.e-codices.unifr.ch/en/csg/0246/37",
            "width": 112.5,
            "height": 150,
            "label": "p. 37"
        },
        {
            "id": "155502",
            "src": "https://www.e-codices.unifr.ch/loris/csg/csg-0246/csg-0246_038.jp2/full/,150/0/default/jpg",
            "href": "https://www.e-codices.unifr.ch/en/csg/0246/38",
            "width": 112.5,
            "height": 150,
            "label": "p. 38"
        },
        {
            "id": "155503",
            "src": "https://www.e-codices.unifr.ch/loris/csg/csg-0246/csg-0246_039.jp2/full/,150/0/default/jpg",
            "href": "https://www.e-codices.unifr.ch/en/csg/0246/39",
            "width": 112.5,
            "height": 150,
            "label": "p. 39"
        },
        {
            "id": "155504",
            "src": "https://www.e-codices.unifr.ch/loris/csg/csg-0246/csg-0246_040.jp2/full/,150/0/default/jpg",
            "href": "https://www.e-codices.unifr.ch/en/csg/0246/40",
            "width": 112.5,
            "height": 150,
            "label": "p. 40"
        },
        {
            "id": "155505",
            "src": "https://www.e-codices.unifr.ch/loris/csg/csg-0246/csg-0246_041.jp2/full/,150/0/default/jpg",
            "href": "https://www.e-codices.unifr.ch/en/csg/0246/41",
            "width": 112.5,
            "height": 150,
            "label": "p. 41"
        },
        {
            "id": "155506",
            "src": "https://www.e-codices.unifr.ch/loris/csg/csg-0246/csg-0246_042.jp2/full/,150/0/default/jpg",
            "href": "https://www.e-codices.unifr.ch/en/csg/0246/42",
            "width": 112.5,
            "height": 150,
            "label": "p. 42"
        },
        {
            "id": "155507",
            "src": "https://www.e-codices.unifr.ch/loris/csg/csg-0246/csg-0246_043.jp2/full/,150/0/default/jpg",
            "href": "https://www.e-codices.unifr.ch/en/csg/0246/43",
            "width": 112.5,
            "height": 150,
            "label": "p. 43"
        },
        {
            "id": "155508",
            "src": "https://www.e-codices.unifr.ch/loris/csg/csg-0246/csg-0246_044.jp2/full/,150/0/default/jpg",
            "href": "https://www.e-codices.unifr.ch/en/csg/0246/44",
            "width": 112.5,
            "height": 150,
            "label": "p. 44"
        },
        {
            "id": "155509",
            "src": "https://www.e-codices.unifr.ch/loris/csg/csg-0246/csg-0246_045.jp2/full/,150/0/default/jpg",
            "href": "https://www.e-codices.unifr.ch/en/csg/0246/45",
            "width": 112.5,
            "height": 150,
            "label": "p. 45"
        },
        {
            "id": "155510",
            "src": "https://www.e-codices.unifr.ch/loris/csg/csg-0246/csg-0246_046.jp2/full/,150/0/default/jpg",
            "href": "https://www.e-codices.unifr.ch/en/csg/0246/46",
            "width": 112.5,
            "height": 150,
            "label": "p. 46"
        },
        {
            "id": "155511",
            "src": "https://www.e-codices.unifr.ch/loris/csg/csg-0246/csg-0246_047.jp2/full/,150/0/default/jpg",
            "href": "https://www.e-codices.unifr.ch/en/csg/0246/47",
            "width": 112.5,
            "height": 150,
            "label": "p. 47"
        },
        {
            "id": "155512",
            "src": "https://www.e-codices.unifr.ch/loris/csg/csg-0246/csg-0246_048.jp2/full/,150/0/default/jpg",
            "href": "https://www.e-codices.unifr.ch/en/csg/0246/48",
            "width": 112.5,
            "height": 150,
            "label": "p. 48"
        },
        {
            "id": "155513",
            "src": "https://www.e-codices.unifr.ch/loris/csg/csg-0246/csg-0246_049.jp2/full/,150/0/default/jpg",
            "href": "https://www.e-codices.unifr.ch/en/csg/0246/49",
            "width": 112.5,
            "height": 150,
            "label": "p. 49"
        },
        {
            "id": "155514",
            "src": "https://www.e-codices.unifr.ch/loris/csg/csg-0246/csg-0246_050.jp2/full/,150/0/default/jpg",
            "href": "https://www.e-codices.unifr.ch/en/csg/0246/50",
            "width": 112.5,
            "height": 150,
            "label": "p. 50"
        },
        {
            "id": "155515",
            "src": "https://www.e-codices.unifr.ch/loris/csg/csg-0246/csg-0246_051.jp2/full/,150/0/default/jpg",
            "href": "https://www.e-codices.unifr.ch/en/csg/0246/51",
            "width": 112.5,
            "height": 150,
            "label": "p. 51"
        },
        {
            "id": "155516",
            "src": "https://www.e-codices.unifr.ch/loris/csg/csg-0246/csg-0246_052.jp2/full/,150/0/default/jpg",
            "href": "https://www.e-codices.unifr.ch/en/csg/0246/52",
            "width": 112.5,
            "height": 150,
            "label": "p. 52"
        },
        {
            "id": "155517",
            "src": "https://www.e-codices.unifr.ch/loris/csg/csg-0246/csg-0246_053.jp2/full/,150/0/default/jpg",
            "href": "https://www.e-codices.unifr.ch/en/csg/0246/53",
            "width": 112.5,
            "height": 150,
            "label": "p. 53"
        },
        {
            "id": "155518",
            "src": "https://www.e-codices.unifr.ch/loris/csg/csg-0246/csg-0246_054.jp2/full/,150/0/default/jpg",
            "href": "https://www.e-codices.unifr.ch/en/csg/0246/54",
            "width": 112.5,
            "height": 150,
            "label": "p. 54"
        },
        {
            "id": "155519",
            "src": "https://www.e-codices.unifr.ch/loris/csg/csg-0246/csg-0246_055.jp2/full/,150/0/default/jpg",
            "href": "https://www.e-codices.unifr.ch/en/csg/0246/55",
            "width": 112.5,
            "height": 150,
            "label": "p. 55"
        },
        {
            "id": "155520",
            "src": "https://www.e-codices.unifr.ch/loris/csg/csg-0246/csg-0246_056.jp2/full/,150/0/default/jpg",
            "href": "https://www.e-codices.unifr.ch/en/csg/0246/56",
            "width": 112.5,
            "height": 150,
            "label": "p. 56"
        },
        {
            "id": "155521",
            "src": "https://www.e-codices.unifr.ch/loris/csg/csg-0246/csg-0246_057.jp2/full/,150/0/default/jpg",
            "href": "https://www.e-codices.unifr.ch/en/csg/0246/57",
            "width": 112.5,
            "height": 150,
            "label": "p. 57"
        },
        {
            "id": "155522",
            "src": "https://www.e-codices.unifr.ch/loris/csg/csg-0246/csg-0246_058.jp2/full/,150/0/default/jpg",
            "href": "https://www.e-codices.unifr.ch/en/csg/0246/58",
            "width": 112.5,
            "height": 150,
            "label": "p. 58"
        },
        {
            "id": "155523",
            "src": "https://www.e-codices.unifr.ch/loris/csg/csg-0246/csg-0246_059.jp2/full/,150/0/default/jpg",
            "href": "https://www.e-codices.unifr.ch/en/csg/0246/59",
            "width": 112.5,
            "height": 150,
            "label": "p. 59"
        },
        {
            "id": "155524",
            "src": "https://www.e-codices.unifr.ch/loris/csg/csg-0246/csg-0246_060.jp2/full/,150/0/default/jpg",
            "href": "https://www.e-codices.unifr.ch/en/csg/0246/60",
            "width": 112.5,
            "height": 150,
            "label": "p. 60"
        },
        {
            "id": "155525",
            "src": "https://www.e-codices.unifr.ch/loris/csg/csg-0246/csg-0246_061.jp2/full/,150/0/default/jpg",
            "href": "https://www.e-codices.unifr.ch/en/csg/0246/61",
            "width": 112.5,
            "height": 150,
            "label": "p. 61"
        },
        {
            "id": "155526",
            "src": "https://www.e-codices.unifr.ch/loris/csg/csg-0246/csg-0246_062.jp2/full/,150/0/default/jpg",
            "href": "https://www.e-codices.unifr.ch/en/csg/0246/62",
            "width": 112.5,
            "height": 150,
            "label": "p. 62"
        },
        {
            "id": "155527",
            "src": "https://www.e-codices.unifr.ch/loris/csg/csg-0246/csg-0246_063.jp2/full/,150/0/default/jpg",
            "href": "https://www.e-codices.unifr.ch/en/csg/0246/63",
            "width": 112.5,
            "height": 150,
            "label": "p. 63"
        },
        {
            "id": "155528",
            "src": "https://www.e-codices.unifr.ch/loris/csg/csg-0246/csg-0246_064.jp2/full/,150/0/default/jpg",
            "href": "https://www.e-codices.unifr.ch/en/csg/0246/64",
            "width": 112.5,
            "height": 150,
            "label": "p. 64"
        },
        {
            "id": "155529",
            "src": "https://www.e-codices.unifr.ch/loris/csg/csg-0246/csg-0246_065.jp2/full/,150/0/default/jpg",
            "href": "https://www.e-codices.unifr.ch/en/csg/0246/65",
            "width": 112.5,
            "height": 150,
            "label": "p. 65"
        },
        {
            "id": "155530",
            "src": "https://www.e-codices.unifr.ch/loris/csg/csg-0246/csg-0246_066.jp2/full/,150/0/default/jpg",
            "href": "https://www.e-codices.unifr.ch/en/csg/0246/66",
            "width": 112.5,
            "height": 150,
            "label": "p. 66"
        },
        {
            "id": "155531",
            "src": "https://www.e-codices.unifr.ch/loris/csg/csg-0246/csg-0246_067.jp2/full/,150/0/default/jpg",
            "href": "https://www.e-codices.unifr.ch/en/csg/0246/67",
            "width": 112.5,
            "height": 150,
            "label": "p. 67"
        },
        {
            "id": "155532",
            "src": "https://www.e-codices.unifr.ch/loris/csg/csg-0246/csg-0246_068.jp2/full/,150/0/default/jpg",
            "href": "https://www.e-codices.unifr.ch/en/csg/0246/68",
            "width": 112.5,
            "height": 150,
            "label": "p. 68"
        },
        {
            "id": "155533",
            "src": "https://www.e-codices.unifr.ch/loris/csg/csg-0246/csg-0246_069.jp2/full/,150/0/default/jpg",
            "href": "https://www.e-codices.unifr.ch/en/csg/0246/69",
            "width": 112.5,
            "height": 150,
            "label": "p. 69"
        },
        {
            "id": "155534",
            "src": "https://www.e-codices.unifr.ch/loris/csg/csg-0246/csg-0246_070.jp2/full/,150/0/default/jpg",
            "href": "https://www.e-codices.unifr.ch/en/csg/0246/70",
            "width": 112.5,
            "height": 150,
            "label": "p. 70"
        },
        {
            "id": "155535",
            "src": "https://www.e-codices.unifr.ch/loris/csg/csg-0246/csg-0246_071.jp2/full/,150/0/default/jpg",
            "href": "https://www.e-codices.unifr.ch/en/csg/0246/71",
            "width": 112.5,
            "height": 150,
            "label": "p. 71"
        },
        {
            "id": "155536",
            "src": "https://www.e-codices.unifr.ch/loris/csg/csg-0246/csg-0246_072.jp2/full/,150/0/default/jpg",
            "href": "https://www.e-codices.unifr.ch/en/csg/0246/72",
            "width": 112.5,
            "height": 150,
            "label": "p. 72"
        },
        {
            "id": "155537",
            "src": "https://www.e-codices.unifr.ch/loris/csg/csg-0246/csg-0246_073.jp2/full/,150/0/default/jpg",
            "href": "https://www.e-codices.unifr.ch/en/csg/0246/73",
            "width": 112.5,
            "height": 150,
            "label": "p. 73"
        },
        {
            "id": "155538",
            "src": "https://www.e-codices.unifr.ch/loris/csg/csg-0246/csg-0246_074.jp2/full/,150/0/default/jpg",
            "href": "https://www.e-codices.unifr.ch/en/csg/0246/74",
            "width": 112.5,
            "height": 150,
            "label": "p. 74"
        },
        {
            "id": "155539",
            "src": "https://www.e-codices.unifr.ch/loris/csg/csg-0246/csg-0246_075.jp2/full/,150/0/default/jpg",
            "href": "https://www.e-codices.unifr.ch/en/csg/0246/75",
            "width": 112.5,
            "height": 150,
            "label": "p. 75"
        },
        {
            "id": "155540",
            "src": "https://www.e-codices.unifr.ch/loris/csg/csg-0246/csg-0246_076.jp2/full/,150/0/default/jpg",
            "href": "https://www.e-codices.unifr.ch/en/csg/0246/76",
            "width": 112.5,
            "height": 150,
            "label": "p. 76"
        },
        {
            "id": "155541",
            "src": "https://www.e-codices.unifr.ch/loris/csg/csg-0246/csg-0246_077.jp2/full/,150/0/default/jpg",
            "href": "https://www.e-codices.unifr.ch/en/csg/0246/77",
            "width": 112.5,
            "height": 150,
            "label": "p. 77"
        },
        {
            "id": "155542",
            "src": "https://www.e-codices.unifr.ch/loris/csg/csg-0246/csg-0246_078.jp2/full/,150/0/default/jpg",
            "href": "https://www.e-codices.unifr.ch/en/csg/0246/78",
            "width": 112.5,
            "height": 150,
            "label": "p. 78"
        },
        {
            "id": "155543",
            "src": "https://www.e-codices.unifr.ch/loris/csg/csg-0246/csg-0246_079.jp2/full/,150/0/default/jpg",
            "href": "https://www.e-codices.unifr.ch/en/csg/0246/79",
            "width": 112.5,
            "height": 150,
            "label": "p. 79"
        },
        {
            "id": "155544",
            "src": "https://www.e-codices.unifr.ch/loris/csg/csg-0246/csg-0246_080.jp2/full/,150/0/default/jpg",
            "href": "https://www.e-codices.unifr.ch/en/csg/0246/80",
            "width": 112.5,
            "height": 150,
            "label": "p. 80"
        },
        {
            "id": "155545",
            "src": "https://www.e-codices.unifr.ch/loris/csg/csg-0246/csg-0246_081.jp2/full/,150/0/default/jpg",
            "href": "https://www.e-codices.unifr.ch/en/csg/0246/81",
            "width": 112.5,
            "height": 150,
            "label": "p. 81"
        },
        {
            "id": "155546",
            "src": "https://www.e-codices.unifr.ch/loris/csg/csg-0246/csg-0246_082.jp2/full/,150/0/default/jpg",
            "href": "https://www.e-codices.unifr.ch/en/csg/0246/82",
            "width": 112.5,
            "height": 150,
            "label": "p. 82"
        },
        {
            "id": "155547",
            "src": "https://www.e-codices.unifr.ch/loris/csg/csg-0246/csg-0246_083.jp2/full/,150/0/default/jpg",
            "href": "https://www.e-codices.unifr.ch/en/csg/0246/83",
            "width": 112.5,
            "height": 150,
            "label": "p. 83"
        },
        {
            "id": "155548",
            "src": "https://www.e-codices.unifr.ch/loris/csg/csg-0246/csg-0246_084.jp2/full/,150/0/default/jpg",
            "href": "https://www.e-codices.unifr.ch/en/csg/0246/84",
            "width": 112.5,
            "height": 150,
            "label": "p. 84"
        },
        {
            "id": "155549",
            "src": "https://www.e-codices.unifr.ch/loris/csg/csg-0246/csg-0246_085.jp2/full/,150/0/default/jpg",
            "href": "https://www.e-codices.unifr.ch/en/csg/0246/85",
            "width": 112.5,
            "height": 150,
            "label": "p. 85"
        },
        {
            "id": "155550",
            "src": "https://www.e-codices.unifr.ch/loris/csg/csg-0246/csg-0246_086.jp2/full/,150/0/default/jpg",
            "href": "https://www.e-codices.unifr.ch/en/csg/0246/86",
            "width": 112.5,
            "height": 150,
            "label": "p. 86"
        },
        {
            "id": "155551",
            "src": "https://www.e-codices.unifr.ch/loris/csg/csg-0246/csg-0246_087.jp2/full/,150/0/default/jpg",
            "href": "https://www.e-codices.unifr.ch/en/csg/0246/87",
            "width": 112.5,
            "height": 150,
            "label": "p. 87"
        },
        {
            "id": "155552",
            "src": "https://www.e-codices.unifr.ch/loris/csg/csg-0246/csg-0246_088.jp2/full/,150/0/default/jpg",
            "href": "https://www.e-codices.unifr.ch/en/csg/0246/88",
            "width": 112.5,
            "height": 150,
            "label": "p. 88"
        },
        {
            "id": "155553",
            "src": "https://www.e-codices.unifr.ch/loris/csg/csg-0246/csg-0246_089.jp2/full/,150/0/default/jpg",
            "href": "https://www.e-codices.unifr.ch/en/csg/0246/89",
            "width": 112.5,
            "height": 150,
            "label": "p. 89"
        },
        {
            "id": "155554",
            "src": "https://www.e-codices.unifr.ch/loris/csg/csg-0246/csg-0246_090.jp2/full/,150/0/default/jpg",
            "href": "https://www.e-codices.unifr.ch/en/csg/0246/90",
            "width": 112.5,
            "height": 150,
            "label": "p. 90"
        },
        {
            "id": "155555",
            "src": "https://www.e-codices.unifr.ch/loris/csg/csg-0246/csg-0246_091.jp2/full/,150/0/default/jpg",
            "href": "https://www.e-codices.unifr.ch/en/csg/0246/91",
            "width": 112.5,
            "height": 150,
            "label": "p. 91"
        },
        {
            "id": "155556",
            "src": "https://www.e-codices.unifr.ch/loris/csg/csg-0246/csg-0246_092.jp2/full/,150/0/default/jpg",
            "href": "https://www.e-codices.unifr.ch/en/csg/0246/92",
            "width": 112.5,
            "height": 150,
            "label": "p. 92"
        },
        {
            "id": "155557",
            "src": "https://www.e-codices.unifr.ch/loris/csg/csg-0246/csg-0246_093.jp2/full/,150/0/default/jpg",
            "href": "https://www.e-codices.unifr.ch/en/csg/0246/93",
            "width": 112.5,
            "height": 150,
            "label": "p. 93"
        },
        {
            "id": "155558",
            "src": "https://www.e-codices.unifr.ch/loris/csg/csg-0246/csg-0246_094.jp2/full/,150/0/default/jpg",
            "href": "https://www.e-codices.unifr.ch/en/csg/0246/94",
            "width": 112.5,
            "height": 150,
            "label": "p. 94"
        },
        {
            "id": "155559",
            "src": "https://www.e-codices.unifr.ch/loris/csg/csg-0246/csg-0246_095.jp2/full/,150/0/default/jpg",
            "href": "https://www.e-codices.unifr.ch/en/csg/0246/95",
            "width": 112.5,
            "height": 150,
            "label": "p. 95"
        },
        {
            "id": "155560",
            "src": "https://www.e-codices.unifr.ch/loris/csg/csg-0246/csg-0246_096.jp2/full/,150/0/default/jpg",
            "href": "https://www.e-codices.unifr.ch/en/csg/0246/96",
            "width": 112.5,
            "height": 150,
            "label": "p. 96"
        },
        {
            "id": "155561",
            "src": "https://www.e-codices.unifr.ch/loris/csg/csg-0246/csg-0246_097.jp2/full/,150/0/default/jpg",
            "href": "https://www.e-codices.unifr.ch/en/csg/0246/97",
            "width": 112.5,
            "height": 150,
            "label": "p. 97"
        },
        {
            "id": "155562",
            "src": "https://www.e-codices.unifr.ch/loris/csg/csg-0246/csg-0246_098.jp2/full/,150/0/default/jpg",
            "href": "https://www.e-codices.unifr.ch/en/csg/0246/98",
            "width": 112.5,
            "height": 150,
            "label": "p. 98"
        },
        {
            "id": "155563",
            "src": "https://www.e-codices.unifr.ch/loris/csg/csg-0246/csg-0246_099.jp2/full/,150/0/default/jpg",
            "href": "https://www.e-codices.unifr.ch/en/csg/0246/99",
            "width": 112.5,
            "height": 150,
            "label": "p. 99"
        },
        {
            "id": "155564",
            "src": "https://www.e-codices.unifr.ch/loris/csg/csg-0246/csg-0246_100.jp2/full/,150/0/default/jpg",
            "href": "https://www.e-codices.unifr.ch/en/csg/0246/100",
            "width": 112.5,
            "height": 150,
            "label": "p. 100"
        },
        {
            "id": "155565",
            "src": "https://www.e-codices.unifr.ch/loris/csg/csg-0246/csg-0246_101.jp2/full/,150/0/default/jpg",
            "href": "https://www.e-codices.unifr.ch/en/csg/0246/101",
            "width": 112.5,
            "height": 150,
            "label": "p. 101"
        },
        {
            "id": "155566",
            "src": "https://www.e-codices.unifr.ch/loris/csg/csg-0246/csg-0246_102.jp2/full/,150/0/default/jpg",
            "href": "https://www.e-codices.unifr.ch/en/csg/0246/102",
            "width": 112.5,
            "height": 150,
            "label": "p. 102"
        },
        {
            "id": "155567",
            "src": "https://www.e-codices.unifr.ch/loris/csg/csg-0246/csg-0246_103.jp2/full/,150/0/default/jpg",
            "href": "https://www.e-codices.unifr.ch/en/csg/0246/103",
            "width": 112.5,
            "height": 150,
            "label": "p. 103"
        },
        {
            "id": "155568",
            "src": "https://www.e-codices.unifr.ch/loris/csg/csg-0246/csg-0246_104.jp2/full/,150/0/default/jpg",
            "href": "https://www.e-codices.unifr.ch/en/csg/0246/104",
            "width": 112.5,
            "height": 150,
            "label": "p. 104"
        },
        {
            "id": "155569",
            "src": "https://www.e-codices.unifr.ch/loris/csg/csg-0246/csg-0246_105.jp2/full/,150/0/default/jpg",
            "href": "https://www.e-codices.unifr.ch/en/csg/0246/105",
            "width": 112.5,
            "height": 150,
            "label": "p. 105"
        },
        {
            "id": "155570",
            "src": "https://www.e-codices.unifr.ch/loris/csg/csg-0246/csg-0246_106.jp2/full/,150/0/default/jpg",
            "href": "https://www.e-codices.unifr.ch/en/csg/0246/106",
            "width": 112.5,
            "height": 150,
            "label": "p. 106"
        },
        {
            "id": "155571",
            "src": "https://www.e-codices.unifr.ch/loris/csg/csg-0246/csg-0246_107.jp2/full/,150/0/default/jpg",
            "href": "https://www.e-codices.unifr.ch/en/csg/0246/107",
            "width": 112.5,
            "height": 150,
            "label": "p. 107"
        },
        {
            "id": "155572",
            "src": "https://www.e-codices.unifr.ch/loris/csg/csg-0246/csg-0246_108.jp2/full/,150/0/default/jpg",
            "href": "https://www.e-codices.unifr.ch/en/csg/0246/108",
            "width": 112.5,
            "height": 150,
            "label": "p. 108"
        },
        {
            "id": "155573",
            "src": "https://www.e-codices.unifr.ch/loris/csg/csg-0246/csg-0246_109.jp2/full/,150/0/default/jpg",
            "href": "https://www.e-codices.unifr.ch/en/csg/0246/109",
            "width": 112.5,
            "height": 150,
            "label": "p. 109"
        },
        {
            "id": "155574",
            "src": "https://www.e-codices.unifr.ch/loris/csg/csg-0246/csg-0246_110.jp2/full/,150/0/default/jpg",
            "href": "https://www.e-codices.unifr.ch/en/csg/0246/110",
            "width": 112.5,
            "height": 150,
            "label": "p. 110"
        },
        {
            "id": "155575",
            "src": "https://www.e-codices.unifr.ch/loris/csg/csg-0246/csg-0246_111.jp2/full/,150/0/default/jpg",
            "href": "https://www.e-codices.unifr.ch/en/csg/0246/111",
            "width": 112.5,
            "height": 150,
            "label": "p. 111"
        },
        {
            "id": "155576",
            "src": "https://www.e-codices.unifr.ch/loris/csg/csg-0246/csg-0246_112.jp2/full/,150/0/default/jpg",
            "href": "https://www.e-codices.unifr.ch/en/csg/0246/112",
            "width": 112.5,
            "height": 150,
            "label": "p. 112"
        },
        {
            "id": "155577",
            "src": "https://www.e-codices.unifr.ch/loris/csg/csg-0246/csg-0246_113.jp2/full/,150/0/default/jpg",
            "href": "https://www.e-codices.unifr.ch/en/csg/0246/113",
            "width": 112.5,
            "height": 150,
            "label": "p. 113"
        },
        {
            "id": "155578",
            "src": "https://www.e-codices.unifr.ch/loris/csg/csg-0246/csg-0246_114.jp2/full/,150/0/default/jpg",
            "href": "https://www.e-codices.unifr.ch/en/csg/0246/114",
            "width": 112.5,
            "height": 150,
            "label": "p. 114"
        },
        {
            "id": "155579",
            "src": "https://www.e-codices.unifr.ch/loris/csg/csg-0246/csg-0246_115.jp2/full/,150/0/default/jpg",
            "href": "https://www.e-codices.unifr.ch/en/csg/0246/115",
            "width": 112.5,
            "height": 150,
            "label": "p. 115"
        },
        {
            "id": "155580",
            "src": "https://www.e-codices.unifr.ch/loris/csg/csg-0246/csg-0246_116.jp2/full/,150/0/default/jpg",
            "href": "https://www.e-codices.unifr.ch/en/csg/0246/116",
            "width": 112.5,
            "height": 150,
            "label": "p. 116"
        },
        {
            "id": "155581",
            "src": "https://www.e-codices.unifr.ch/loris/csg/csg-0246/csg-0246_117.jp2/full/,150/0/default/jpg",
            "href": "https://www.e-codices.unifr.ch/en/csg/0246/117",
            "width": 112.5,
            "height": 150,
            "label": "p. 117"
        },
        {
            "id": "155582",
            "src": "https://www.e-codices.unifr.ch/loris/csg/csg-0246/csg-0246_118.jp2/full/,150/0/default/jpg",
            "href": "https://www.e-codices.unifr.ch/en/csg/0246/118",
            "width": 112.5,
            "height": 150,
            "label": "p. 118"
        },
        {
            "id": "155583",
            "src": "https://www.e-codices.unifr.ch/loris/csg/csg-0246/csg-0246_119.jp2/full/,150/0/default/jpg",
            "href": "https://www.e-codices.unifr.ch/en/csg/0246/119",
            "width": 112.5,
            "height": 150,
            "label": "p. 119"
        },
        {
            "id": "155584",
            "src": "https://www.e-codices.unifr.ch/loris/csg/csg-0246/csg-0246_120.jp2/full/,150/0/default/jpg",
            "href": "https://www.e-codices.unifr.ch/en/csg/0246/120",
            "width": 112.5,
            "height": 150,
            "label": "p. 120"
        },
        {
            "id": "155585",
            "src": "https://www.e-codices.unifr.ch/loris/csg/csg-0246/csg-0246_121.jp2/full/,150/0/default/jpg",
            "href": "https://www.e-codices.unifr.ch/en/csg/0246/121",
            "width": 112.5,
            "height": 150,
            "label": "p. 121"
        },
        {
            "id": "155586",
            "src": "https://www.e-codices.unifr.ch/loris/csg/csg-0246/csg-0246_122.jp2/full/,150/0/default/jpg",
            "href": "https://www.e-codices.unifr.ch/en/csg/0246/122",
            "width": 112.5,
            "height": 150,
            "label": "p. 122"
        },
        {
            "id": "155587",
            "src": "https://www.e-codices.unifr.ch/loris/csg/csg-0246/csg-0246_123.jp2/full/,150/0/default/jpg",
            "href": "https://www.e-codices.unifr.ch/en/csg/0246/123",
            "width": 112.5,
            "height": 150,
            "label": "p. 123"
        },
        {
            "id": "155588",
            "src": "https://www.e-codices.unifr.ch/loris/csg/csg-0246/csg-0246_124.jp2/full/,150/0/default/jpg",
            "href": "https://www.e-codices.unifr.ch/en/csg/0246/124",
            "width": 112.5,
            "height": 150,
            "label": "p. 124"
        },
        {
            "id": "155589",
            "src": "https://www.e-codices.unifr.ch/loris/csg/csg-0246/csg-0246_125.jp2/full/,150/0/default/jpg",
            "href": "https://www.e-codices.unifr.ch/en/csg/0246/125",
            "width": 112.5,
            "height": 150,
            "label": "p. 125"
        },
        {
            "id": "155590",
            "src": "https://www.e-codices.unifr.ch/loris/csg/csg-0246/csg-0246_126.jp2/full/,150/0/default/jpg",
            "href": "https://www.e-codices.unifr.ch/en/csg/0246/126",
            "width": 112.5,
            "height": 150,
            "label": "p. 126"
        },
        {
            "id": "155591",
            "src": "https://www.e-codices.unifr.ch/loris/csg/csg-0246/csg-0246_127.jp2/full/,150/0/default/jpg",
            "href": "https://www.e-codices.unifr.ch/en/csg/0246/127",
            "width": 112.5,
            "height": 150,
            "label": "p. 127"
        },
        {
            "id": "155592",
            "src": "https://www.e-codices.unifr.ch/loris/csg/csg-0246/csg-0246_128.jp2/full/,150/0/default/jpg",
            "href": "https://www.e-codices.unifr.ch/en/csg/0246/128",
            "width": 112.5,
            "height": 150,
            "label": "p. 128"
        },
        {
            "id": "155593",
            "src": "https://www.e-codices.unifr.ch/loris/csg/csg-0246/csg-0246_129.jp2/full/,150/0/default/jpg",
            "href": "https://www.e-codices.unifr.ch/en/csg/0246/129",
            "width": 112.5,
            "height": 150,
            "label": "p. 129"
        },
        {
            "id": "155594",
            "src": "https://www.e-codices.unifr.ch/loris/csg/csg-0246/csg-0246_130.jp2/full/,150/0/default/jpg",
            "href": "https://www.e-codices.unifr.ch/en/csg/0246/130",
            "width": 112.5,
            "height": 150,
            "label": "p. 130"
        },
        {
            "id": "155595",
            "src": "https://www.e-codices.unifr.ch/loris/csg/csg-0246/csg-0246_131.jp2/full/,150/0/default/jpg",
            "href": "https://www.e-codices.unifr.ch/en/csg/0246/131",
            "width": 112.5,
            "height": 150,
            "label": "p. 131"
        },
        {
            "id": "155596",
            "src": "https://www.e-codices.unifr.ch/loris/csg/csg-0246/csg-0246_132.jp2/full/,150/0/default/jpg",
            "href": "https://www.e-codices.unifr.ch/en/csg/0246/132",
            "width": 112.5,
            "height": 150,
            "label": "p. 132"
        },
        {
            "id": "155597",
            "src": "https://www.e-codices.unifr.ch/loris/csg/csg-0246/csg-0246_133.jp2/full/,150/0/default/jpg",
            "href": "https://www.e-codices.unifr.ch/en/csg/0246/133",
            "width": 112.5,
            "height": 150,
            "label": "p. 133"
        },
        {
            "id": "155598",
            "src": "https://www.e-codices.unifr.ch/loris/csg/csg-0246/csg-0246_134.jp2/full/,150/0/default/jpg",
            "href": "https://www.e-codices.unifr.ch/en/csg/0246/134",
            "width": 112.5,
            "height": 150,
            "label": "p. 134"
        },
        {
            "id": "155599",
            "src": "https://www.e-codices.unifr.ch/loris/csg/csg-0246/csg-0246_135.jp2/full/,150/0/default/jpg",
            "href": "https://www.e-codices.unifr.ch/en/csg/0246/135",
            "width": 112.5,
            "height": 150,
            "label": "p. 135"
        },
        {
            "id": "155600",
            "src": "https://www.e-codices.unifr.ch/loris/csg/csg-0246/csg-0246_136.jp2/full/,150/0/default/jpg",
            "href": "https://www.e-codices.unifr.ch/en/csg/0246/136",
            "width": 112.5,
            "height": 150,
            "label": "p. 136"
        },
        {
            "id": "155601",
            "src": "https://www.e-codices.unifr.ch/loris/csg/csg-0246/csg-0246_137.jp2/full/,150/0/default/jpg",
            "href": "https://www.e-codices.unifr.ch/en/csg/0246/137",
            "width": 112.5,
            "height": 150,
            "label": "p. 137"
        },
        {
            "id": "155602",
            "src": "https://www.e-codices.unifr.ch/loris/csg/csg-0246/csg-0246_138.jp2/full/,150/0/default/jpg",
            "href": "https://www.e-codices.unifr.ch/en/csg/0246/138",
            "width": 112.5,
            "height": 150,
            "label": "p. 138"
        },
        {
            "id": "155603",
            "src": "https://www.e-codices.unifr.ch/loris/csg/csg-0246/csg-0246_139.jp2/full/,150/0/default/jpg",
            "href": "https://www.e-codices.unifr.ch/en/csg/0246/139",
            "width": 112.5,
            "height": 150,
            "label": "p. 139"
        },
        {
            "id": "155604",
            "src": "https://www.e-codices.unifr.ch/loris/csg/csg-0246/csg-0246_140.jp2/full/,150/0/default/jpg",
            "href": "https://www.e-codices.unifr.ch/en/csg/0246/140",
            "width": 112.5,
            "height": 150,
            "label": "p. 140"
        },
        {
            "id": "155605",
            "src": "https://www.e-codices.unifr.ch/loris/csg/csg-0246/csg-0246_141.jp2/full/,150/0/default/jpg",
            "href": "https://www.e-codices.unifr.ch/en/csg/0246/141",
            "width": 112.5,
            "height": 150,
            "label": "p. 141"
        },
        {
            "id": "155606",
            "src": "https://www.e-codices.unifr.ch/loris/csg/csg-0246/csg-0246_142.jp2/full/,150/0/default/jpg",
            "href": "https://www.e-codices.unifr.ch/en/csg/0246/142",
            "width": 112.5,
            "height": 150,
            "label": "p. 142"
        },
        {
            "id": "155607",
            "src": "https://www.e-codices.unifr.ch/loris/csg/csg-0246/csg-0246_143.jp2/full/,150/0/default/jpg",
            "href": "https://www.e-codices.unifr.ch/en/csg/0246/143",
            "width": 112.5,
            "height": 150,
            "label": "p. 143"
        },
        {
            "id": "155608",
            "src": "https://www.e-codices.unifr.ch/loris/csg/csg-0246/csg-0246_144.jp2/full/,150/0/default/jpg",
            "href": "https://www.e-codices.unifr.ch/en/csg/0246/144",
            "width": 112.5,
            "height": 150,
            "label": "p. 144"
        },
        {
            "id": "155609",
            "src": "https://www.e-codices.unifr.ch/loris/csg/csg-0246/csg-0246_145.jp2/full/,150/0/default/jpg",
            "href": "https://www.e-codices.unifr.ch/en/csg/0246/145",
            "width": 112.5,
            "height": 150,
            "label": "p. 145"
        },
        {
            "id": "155610",
            "src": "https://www.e-codices.unifr.ch/loris/csg/csg-0246/csg-0246_146.jp2/full/,150/0/default/jpg",
            "href": "https://www.e-codices.unifr.ch/en/csg/0246/146",
            "width": 112.5,
            "height": 150,
            "label": "p. 146"
        },
        {
            "id": "155611",
            "src": "https://www.e-codices.unifr.ch/loris/csg/csg-0246/csg-0246_147.jp2/full/,150/0/default/jpg",
            "href": "https://www.e-codices.unifr.ch/en/csg/0246/147",
            "width": 112.5,
            "height": 150,
            "label": "p. 147"
        },
        {
            "id": "155612",
            "src": "https://www.e-codices.unifr.ch/loris/csg/csg-0246/csg-0246_148.jp2/full/,150/0/default/jpg",
            "href": "https://www.e-codices.unifr.ch/en/csg/0246/148",
            "width": 112.5,
            "height": 150,
            "label": "p. 148"
        },
        {
            "id": "155613",
            "src": "https://www.e-codices.unifr.ch/loris/csg/csg-0246/csg-0246_149.jp2/full/,150/0/default/jpg",
            "href": "https://www.e-codices.unifr.ch/en/csg/0246/149",
            "width": 112.5,
            "height": 150,
            "label": "p. 149"
        },
        {
            "id": "155614",
            "src": "https://www.e-codices.unifr.ch/loris/csg/csg-0246/csg-0246_150.jp2/full/,150/0/default/jpg",
            "href": "https://www.e-codices.unifr.ch/en/csg/0246/150",
            "width": 112.5,
            "height": 150,
            "label": "p. 150"
        },
        {
            "id": "155615",
            "src": "https://www.e-codices.unifr.ch/loris/csg/csg-0246/csg-0246_151.jp2/full/,150/0/default/jpg",
            "href": "https://www.e-codices.unifr.ch/en/csg/0246/151",
            "width": 112.5,
            "height": 150,
            "label": "p. 151"
        },
        {
            "id": "155616",
            "src": "https://www.e-codices.unifr.ch/loris/csg/csg-0246/csg-0246_152.jp2/full/,150/0/default/jpg",
            "href": "https://www.e-codices.unifr.ch/en/csg/0246/152",
            "width": 112.5,
            "height": 150,
            "label": "p. 152"
        },
        {
            "id": "155617",
            "src": "https://www.e-codices.unifr.ch/loris/csg/csg-0246/csg-0246_153.jp2/full/,150/0/default/jpg",
            "href": "https://www.e-codices.unifr.ch/en/csg/0246/153",
            "width": 112.5,
            "height": 150,
            "label": "p. 153"
        },
        {
            "id": "155618",
            "src": "https://www.e-codices.unifr.ch/loris/csg/csg-0246/csg-0246_154.jp2/full/,150/0/default/jpg",
            "href": "https://www.e-codices.unifr.ch/en/csg/0246/154",
            "width": 112.5,
            "height": 150,
            "label": "p. 154"
        },
        {
            "id": "155619",
            "src": "https://www.e-codices.unifr.ch/loris/csg/csg-0246/csg-0246_155.jp2/full/,150/0/default/jpg",
            "href": "https://www.e-codices.unifr.ch/en/csg/0246/155",
            "width": 112.5,
            "height": 150,
            "label": "p. 155"
        },
        {
            "id": "155620",
            "src": "https://www.e-codices.unifr.ch/loris/csg/csg-0246/csg-0246_156.jp2/full/,150/0/default/jpg",
            "href": "https://www.e-codices.unifr.ch/en/csg/0246/156",
            "width": 112.5,
            "height": 150,
            "label": "p. 156"
        },
        {
            "id": "155621",
            "src": "https://www.e-codices.unifr.ch/loris/csg/csg-0246/csg-0246_157.jp2/full/,150/0/default/jpg",
            "href": "https://www.e-codices.unifr.ch/en/csg/0246/157",
            "width": 112.5,
            "height": 150,
            "label": "p. 157"
        },
        {
            "id": "155622",
            "src": "https://www.e-codices.unifr.ch/loris/csg/csg-0246/csg-0246_158.jp2/full/,150/0/default/jpg",
            "href": "https://www.e-codices.unifr.ch/en/csg/0246/158",
            "width": 112.5,
            "height": 150,
            "label": "p. 158"
        },
        {
            "id": "155623",
            "src": "https://www.e-codices.unifr.ch/loris/csg/csg-0246/csg-0246_159.jp2/full/,150/0/default/jpg",
            "href": "https://www.e-codices.unifr.ch/en/csg/0246/159",
            "width": 112.5,
            "height": 150,
            "label": "p. 159"
        },
        {
            "id": "155624",
            "src": "https://www.e-codices.unifr.ch/loris/csg/csg-0246/csg-0246_160.jp2/full/,150/0/default/jpg",
            "href": "https://www.e-codices.unifr.ch/en/csg/0246/160",
            "width": 112.5,
            "height": 150,
            "label": "p. 160"
        },
        {
            "id": "155625",
            "src": "https://www.e-codices.unifr.ch/loris/csg/csg-0246/csg-0246_161.jp2/full/,150/0/default/jpg",
            "href": "https://www.e-codices.unifr.ch/en/csg/0246/161",
            "width": 112.5,
            "height": 150,
            "label": "p. 161"
        },
        {
            "id": "155626",
            "src": "https://www.e-codices.unifr.ch/loris/csg/csg-0246/csg-0246_162.jp2/full/,150/0/default/jpg",
            "href": "https://www.e-codices.unifr.ch/en/csg/0246/162",
            "width": 112.5,
            "height": 150,
            "label": "p. 162"
        },
        {
            "id": "155627",
            "src": "https://www.e-codices.unifr.ch/loris/csg/csg-0246/csg-0246_163.jp2/full/,150/0/default/jpg",
            "href": "https://www.e-codices.unifr.ch/en/csg/0246/163",
            "width": 112.5,
            "height": 150,
            "label": "p. 163"
        },
        {
            "id": "155628",
            "src": "https://www.e-codices.unifr.ch/loris/csg/csg-0246/csg-0246_164.jp2/full/,150/0/default/jpg",
            "href": "https://www.e-codices.unifr.ch/en/csg/0246/164",
            "width": 112.5,
            "height": 150,
            "label": "p. 164"
        },
        {
            "id": "155629",
            "src": "https://www.e-codices.unifr.ch/loris/csg/csg-0246/csg-0246_165.jp2/full/,150/0/default/jpg",
            "href": "https://www.e-codices.unifr.ch/en/csg/0246/165",
            "width": 112.5,
            "height": 150,
            "label": "p. 165"
        },
        {
            "id": "155630",
            "src": "https://www.e-codices.unifr.ch/loris/csg/csg-0246/csg-0246_166.jp2/full/,150/0/default/jpg",
            "href": "https://www.e-codices.unifr.ch/en/csg/0246/166",
            "width": 112.5,
            "height": 150,
            "label": "p. 166"
        },
        {
            "id": "155631",
            "src": "https://www.e-codices.unifr.ch/loris/csg/csg-0246/csg-0246_167.jp2/full/,150/0/default/jpg",
            "href": "https://www.e-codices.unifr.ch/en/csg/0246/167",
            "width": 112.5,
            "height": 150,
            "label": "p. 167"
        },
        {
            "id": "155632",
            "src": "https://www.e-codices.unifr.ch/loris/csg/csg-0246/csg-0246_168.jp2/full/,150/0/default/jpg",
            "href": "https://www.e-codices.unifr.ch/en/csg/0246/168",
            "width": 112.5,
            "height": 150,
            "label": "p. 168"
        },
        {
            "id": "155633",
            "src": "https://www.e-codices.unifr.ch/loris/csg/csg-0246/csg-0246_169.jp2/full/,150/0/default/jpg",
            "href": "https://www.e-codices.unifr.ch/en/csg/0246/169",
            "width": 112.5,
            "height": 150,
            "label": "p. 169"
        },
        {
            "id": "155634",
            "src": "https://www.e-codices.unifr.ch/loris/csg/csg-0246/csg-0246_170.jp2/full/,150/0/default/jpg",
            "href": "https://www.e-codices.unifr.ch/en/csg/0246/170",
            "width": 112.5,
            "height": 150,
            "label": "p. 170"
        },
        {
            "id": "155635",
            "src": "https://www.e-codices.unifr.ch/loris/csg/csg-0246/csg-0246_171.jp2/full/,150/0/default/jpg",
            "href": "https://www.e-codices.unifr.ch/en/csg/0246/171",
            "width": 112.5,
            "height": 150,
            "label": "p. 171"
        },
        {
            "id": "155636",
            "src": "https://www.e-codices.unifr.ch/loris/csg/csg-0246/csg-0246_172.jp2/full/,150/0/default/jpg",
            "href": "https://www.e-codices.unifr.ch/en/csg/0246/172",
            "width": 112.5,
            "height": 150,
            "label": "p. 172"
        },
        {
            "id": "155637",
            "src": "https://www.e-codices.unifr.ch/loris/csg/csg-0246/csg-0246_173.jp2/full/,150/0/default/jpg",
            "href": "https://www.e-codices.unifr.ch/en/csg/0246/173",
            "width": 112.5,
            "height": 150,
            "label": "p. 173"
        },
        {
            "id": "155638",
            "src": "https://www.e-codices.unifr.ch/loris/csg/csg-0246/csg-0246_174.jp2/full/,150/0/default/jpg",
            "href": "https://www.e-codices.unifr.ch/en/csg/0246/174",
            "width": 112.5,
            "height": 150,
            "label": "p. 174"
        },
        {
            "id": "155639",
            "src": "https://www.e-codices.unifr.ch/loris/csg/csg-0246/csg-0246_175.jp2/full/,150/0/default/jpg",
            "href": "https://www.e-codices.unifr.ch/en/csg/0246/175",
            "width": 112.5,
            "height": 150,
            "label": "p. 175"
        },
        {
            "id": "155640",
            "src": "https://www.e-codices.unifr.ch/loris/csg/csg-0246/csg-0246_176.jp2/full/,150/0/default/jpg",
            "href": "https://www.e-codices.unifr.ch/en/csg/0246/176",
            "width": 112.5,
            "height": 150,
            "label": "p. 176"
        },
        {
            "id": "155641",
            "src": "https://www.e-codices.unifr.ch/loris/csg/csg-0246/csg-0246_177.jp2/full/,150/0/default/jpg",
            "href": "https://www.e-codices.unifr.ch/en/csg/0246/177",
            "width": 112.5,
            "height": 150,
            "label": "p. 177"
        },
        {
            "id": "155642",
            "src": "https://www.e-codices.unifr.ch/loris/csg/csg-0246/csg-0246_178.jp2/full/,150/0/default/jpg",
            "href": "https://www.e-codices.unifr.ch/en/csg/0246/178",
            "width": 112.5,
            "height": 150,
            "label": "p. 178"
        },
        {
            "id": "155643",
            "src": "https://www.e-codices.unifr.ch/loris/csg/csg-0246/csg-0246_179.jp2/full/,150/0/default/jpg",
            "href": "https://www.e-codices.unifr.ch/en/csg/0246/179",
            "width": 112.5,
            "height": 150,
            "label": "p. 179"
        },
        {
            "id": "155644",
            "src": "https://www.e-codices.unifr.ch/loris/csg/csg-0246/csg-0246_180.jp2/full/,150/0/default/jpg",
            "href": "https://www.e-codices.unifr.ch/en/csg/0246/180",
            "width": 112.5,
            "height": 150,
            "label": "p. 180"
        },
        {
            "id": "155645",
            "src": "https://www.e-codices.unifr.ch/loris/csg/csg-0246/csg-0246_181.jp2/full/,150/0/default/jpg",
            "href": "https://www.e-codices.unifr.ch/en/csg/0246/181",
            "width": 112.5,
            "height": 150,
            "label": "p. 181"
        },
        {
            "id": "155646",
            "src": "https://www.e-codices.unifr.ch/loris/csg/csg-0246/csg-0246_182.jp2/full/,150/0/default/jpg",
            "href": "https://www.e-codices.unifr.ch/en/csg/0246/182",
            "width": 112.5,
            "height": 150,
            "label": "p. 182"
        },
        {
            "id": "155647",
            "src": "https://www.e-codices.unifr.ch/loris/csg/csg-0246/csg-0246_183.jp2/full/,150/0/default/jpg",
            "href": "https://www.e-codices.unifr.ch/en/csg/0246/183",
            "width": 112.5,
            "height": 150,
            "label": "p. 183"
        },
        {
            "id": "155648",
            "src": "https://www.e-codices.unifr.ch/loris/csg/csg-0246/csg-0246_184.jp2/full/,150/0/default/jpg",
            "href": "https://www.e-codices.unifr.ch/en/csg/0246/184",
            "width": 112.5,
            "height": 150,
            "label": "p. 184"
        },
        {
            "id": "155649",
            "src": "https://www.e-codices.unifr.ch/loris/csg/csg-0246/csg-0246_185.jp2/full/,150/0/default/jpg",
            "href": "https://www.e-codices.unifr.ch/en/csg/0246/185",
            "width": 112.5,
            "height": 150,
            "label": "p. 185"
        },
        {
            "id": "155650",
            "src": "https://www.e-codices.unifr.ch/loris/csg/csg-0246/csg-0246_186.jp2/full/,150/0/default/jpg",
            "href": "https://www.e-codices.unifr.ch/en/csg/0246/186",
            "width": 112.5,
            "height": 150,
            "label": "p. 186"
        },
        {
            "id": "155651",
            "src": "https://www.e-codices.unifr.ch/loris/csg/csg-0246/csg-0246_187.jp2/full/,150/0/default/jpg",
            "href": "https://www.e-codices.unifr.ch/en/csg/0246/187",
            "width": 112.5,
            "height": 150,
            "label": "p. 187"
        },
        {
            "id": "155652",
            "src": "https://www.e-codices.unifr.ch/loris/csg/csg-0246/csg-0246_188.jp2/full/,150/0/default/jpg",
            "href": "https://www.e-codices.unifr.ch/en/csg/0246/188",
            "width": 112.5,
            "height": 150,
            "label": "p. 188"
        },
        {
            "id": "155653",
            "src": "https://www.e-codices.unifr.ch/loris/csg/csg-0246/csg-0246_189.jp2/full/,150/0/default/jpg",
            "href": "https://www.e-codices.unifr.ch/en/csg/0246/189",
            "width": 112.5,
            "height": 150,
            "label": "p. 189"
        },
        {
            "id": "155654",
            "src": "https://www.e-codices.unifr.ch/loris/csg/csg-0246/csg-0246_190.jp2/full/,150/0/default/jpg",
            "href": "https://www.e-codices.unifr.ch/en/csg/0246/190",
            "width": 112.5,
            "height": 150,
            "label": "p. 190"
        },
        {
            "id": "155655",
            "src": "https://www.e-codices.unifr.ch/loris/csg/csg-0246/csg-0246_191.jp2/full/,150/0/default/jpg",
            "href": "https://www.e-codices.unifr.ch/en/csg/0246/191",
            "width": 112.5,
            "height": 150,
            "label": "p. 191"
        },
        {
            "id": "155656",
            "src": "https://www.e-codices.unifr.ch/loris/csg/csg-0246/csg-0246_192.jp2/full/,150/0/default/jpg",
            "href": "https://www.e-codices.unifr.ch/en/csg/0246/192",
            "width": 112.5,
            "height": 150,
            "label": "p. 192"
        },
        {
            "id": "155657",
            "src": "https://www.e-codices.unifr.ch/loris/csg/csg-0246/csg-0246_193.jp2/full/,150/0/default/jpg",
            "href": "https://www.e-codices.unifr.ch/en/csg/0246/193",
            "width": 112.5,
            "height": 150,
            "label": "p. 193"
        },
        {
            "id": "155658",
            "src": "https://www.e-codices.unifr.ch/loris/csg/csg-0246/csg-0246_194.jp2/full/,150/0/default/jpg",
            "href": "https://www.e-codices.unifr.ch/en/csg/0246/194",
            "width": 112.5,
            "height": 150,
            "label": "p. 194"
        },
        {
            "id": "155659",
            "src": "https://www.e-codices.unifr.ch/loris/csg/csg-0246/csg-0246_195.jp2/full/,150/0/default/jpg",
            "href": "https://www.e-codices.unifr.ch/en/csg/0246/195",
            "width": 112.5,
            "height": 150,
            "label": "p. 195"
        },
        {
            "id": "155660",
            "src": "https://www.e-codices.unifr.ch/loris/csg/csg-0246/csg-0246_196.jp2/full/,150/0/default/jpg",
            "href": "https://www.e-codices.unifr.ch/en/csg/0246/196",
            "width": 112.5,
            "height": 150,
            "label": "p. 196"
        },
        {
            "id": "155661",
            "src": "https://www.e-codices.unifr.ch/loris/csg/csg-0246/csg-0246_197.jp2/full/,150/0/default/jpg",
            "href": "https://www.e-codices.unifr.ch/en/csg/0246/197",
            "width": 112.5,
            "height": 150,
            "label": "p. 197"
        },
        {
            "id": "155662",
            "src": "https://www.e-codices.unifr.ch/loris/csg/csg-0246/csg-0246_198.jp2/full/,150/0/default/jpg",
            "href": "https://www.e-codices.unifr.ch/en/csg/0246/198",
            "width": 112.5,
            "height": 150,
            "label": "p. 198"
        },
        {
            "id": "155663",
            "src": "https://www.e-codices.unifr.ch/loris/csg/csg-0246/csg-0246_199.jp2/full/,150/0/default/jpg",
            "href": "https://www.e-codices.unifr.ch/en/csg/0246/199",
            "width": 112.5,
            "height": 150,
            "label": "p. 199"
        },
        {
            "id": "155664",
            "src": "https://www.e-codices.unifr.ch/loris/csg/csg-0246/csg-0246_200.jp2/full/,150/0/default/jpg",
            "href": "https://www.e-codices.unifr.ch/en/csg/0246/200",
            "width": 112.5,
            "height": 150,
            "label": "p. 200"
        },
        {
            "id": "155665",
            "src": "https://www.e-codices.unifr.ch/loris/csg/csg-0246/csg-0246_201.jp2/full/,150/0/default/jpg",
            "href": "https://www.e-codices.unifr.ch/en/csg/0246/201",
            "width": 112.5,
            "height": 150,
            "label": "p. 201"
        },
        {
            "id": "155666",
            "src": "https://www.e-codices.unifr.ch/loris/csg/csg-0246/csg-0246_202.jp2/full/,150/0/default/jpg",
            "href": "https://www.e-codices.unifr.ch/en/csg/0246/202",
            "width": 112.5,
            "height": 150,
            "label": "p. 202"
        },
        {
            "id": "155667",
            "src": "https://www.e-codices.unifr.ch/loris/csg/csg-0246/csg-0246_203.jp2/full/,150/0/default/jpg",
            "href": "https://www.e-codices.unifr.ch/en/csg/0246/203",
            "width": 112.5,
            "height": 150,
            "label": "p. 203"
        },
        {
            "id": "155668",
            "src": "https://www.e-codices.unifr.ch/loris/csg/csg-0246/csg-0246_204.jp2/full/,150/0/default/jpg",
            "href": "https://www.e-codices.unifr.ch/en/csg/0246/204",
            "width": 112.5,
            "height": 150,
            "label": "p. 204"
        },
        {
            "id": "155669",
            "src": "https://www.e-codices.unifr.ch/loris/csg/csg-0246/csg-0246_205.jp2/full/,150/0/default/jpg",
            "href": "https://www.e-codices.unifr.ch/en/csg/0246/205",
            "width": 112.5,
            "height": 150,
            "label": "p. 205"
        },
        {
            "id": "155670",
            "src": "https://www.e-codices.unifr.ch/loris/csg/csg-0246/csg-0246_206.jp2/full/,150/0/default/jpg",
            "href": "https://www.e-codices.unifr.ch/en/csg/0246/206",
            "width": 112.5,
            "height": 150,
            "label": "p. 206"
        },
        {
            "id": "155671",
            "src": "https://www.e-codices.unifr.ch/loris/csg/csg-0246/csg-0246_207.jp2/full/,150/0/default/jpg",
            "href": "https://www.e-codices.unifr.ch/en/csg/0246/207",
            "width": 112.5,
            "height": 150,
            "label": "p. 207"
        },
        {
            "id": "155672",
            "src": "https://www.e-codices.unifr.ch/loris/csg/csg-0246/csg-0246_208.jp2/full/,150/0/default/jpg",
            "href": "https://www.e-codices.unifr.ch/en/csg/0246/208",
            "width": 112.5,
            "height": 150,
            "label": "p. 208"
        },
        {
            "id": "155673",
            "src": "https://www.e-codices.unifr.ch/loris/csg/csg-0246/csg-0246_209.jp2/full/,150/0/default/jpg",
            "href": "https://www.e-codices.unifr.ch/en/csg/0246/209",
            "width": 112.5,
            "height": 150,
            "label": "p. 209"
        },
        {
            "id": "155674",
            "src": "https://www.e-codices.unifr.ch/loris/csg/csg-0246/csg-0246_210.jp2/full/,150/0/default/jpg",
            "href": "https://www.e-codices.unifr.ch/en/csg/0246/210",
            "width": 112.5,
            "height": 150,
            "label": "p. 210"
        },
        {
            "id": "155675",
            "src": "https://www.e-codices.unifr.ch/loris/csg/csg-0246/csg-0246_211.jp2/full/,150/0/default/jpg",
            "href": "https://www.e-codices.unifr.ch/en/csg/0246/211",
            "width": 112.5,
            "height": 150,
            "label": "p. 211"
        },
        {
            "id": "155676",
            "src": "https://www.e-codices.unifr.ch/loris/csg/csg-0246/csg-0246_212.jp2/full/,150/0/default/jpg",
            "href": "https://www.e-codices.unifr.ch/en/csg/0246/212",
            "width": 112.5,
            "height": 150,
            "label": "p. 212"
        },
        {
            "id": "155677",
            "src": "https://www.e-codices.unifr.ch/loris/csg/csg-0246/csg-0246_213.jp2/full/,150/0/default/jpg",
            "href": "https://www.e-codices.unifr.ch/en/csg/0246/213",
            "width": 112.5,
            "height": 150,
            "label": "p. 213"
        },
        {
            "id": "155678",
            "src": "https://www.e-codices.unifr.ch/loris/csg/csg-0246/csg-0246_214.jp2/full/,150/0/default/jpg",
            "href": "https://www.e-codices.unifr.ch/en/csg/0246/214",
            "width": 112.5,
            "height": 150,
            "label": "p. 214"
        },
        {
            "id": "155679",
            "src": "https://www.e-codices.unifr.ch/loris/csg/csg-0246/csg-0246_215.jp2/full/,150/0/default/jpg",
            "href": "https://www.e-codices.unifr.ch/en/csg/0246/215",
            "width": 112.5,
            "height": 150,
            "label": "p. 215"
        },
        {
            "id": "155680",
            "src": "https://www.e-codices.unifr.ch/loris/csg/csg-0246/csg-0246_216.jp2/full/,150/0/default/jpg",
            "href": "https://www.e-codices.unifr.ch/en/csg/0246/216",
            "width": 112.5,
            "height": 150,
            "label": "p. 216"
        },
        {
            "id": "155681",
            "src": "https://www.e-codices.unifr.ch/loris/csg/csg-0246/csg-0246_217.jp2/full/,150/0/default/jpg",
            "href": "https://www.e-codices.unifr.ch/en/csg/0246/217",
            "width": 112.5,
            "height": 150,
            "label": "p. 217"
        },
        {
            "id": "155682",
            "src": "https://www.e-codices.unifr.ch/loris/csg/csg-0246/csg-0246_218.jp2/full/,150/0/default/jpg",
            "href": "https://www.e-codices.unifr.ch/en/csg/0246/218",
            "width": 112.5,
            "height": 150,
            "label": "p. 218"
        },
        {
            "id": "155683",
            "src": "https://www.e-codices.unifr.ch/loris/csg/csg-0246/csg-0246_219.jp2/full/,150/0/default/jpg",
            "href": "https://www.e-codices.unifr.ch/en/csg/0246/219",
            "width": 112.5,
            "height": 150,
            "label": "p. 219"
        },
        {
            "id": "155684",
            "src": "https://www.e-codices.unifr.ch/loris/csg/csg-0246/csg-0246_220.jp2/full/,150/0/default/jpg",
            "href": "https://www.e-codices.unifr.ch/en/csg/0246/220",
            "width": 112.5,
            "height": 150,
            "label": "p. 220"
        },
        {
            "id": "155685",
            "src": "https://www.e-codices.unifr.ch/loris/csg/csg-0246/csg-0246_221.jp2/full/,150/0/default/jpg",
            "href": "https://www.e-codices.unifr.ch/en/csg/0246/221",
            "width": 112.5,
            "height": 150,
            "label": "p. 221"
        },
        {
            "id": "155686",
            "src": "https://www.e-codices.unifr.ch/loris/csg/csg-0246/csg-0246_222.jp2/full/,150/0/default/jpg",
            "href": "https://www.e-codices.unifr.ch/en/csg/0246/222",
            "width": 112.5,
            "height": 150,
            "label": "p. 222"
        },
        {
            "id": "155687",
            "src": "https://www.e-codices.unifr.ch/loris/csg/csg-0246/csg-0246_223.jp2/full/,150/0/default/jpg",
            "href": "https://www.e-codices.unifr.ch/en/csg/0246/223",
            "width": 112.5,
            "height": 150,
            "label": "p. 223"
        },
        {
            "id": "155688",
            "src": "https://www.e-codices.unifr.ch/loris/csg/csg-0246/csg-0246_224.jp2/full/,150/0/default/jpg",
            "href": "https://www.e-codices.unifr.ch/en/csg/0246/224",
            "width": 112.5,
            "height": 150,
            "label": "p. 224"
        },
        {
            "id": "155689",
            "src": "https://www.e-codices.unifr.ch/loris/csg/csg-0246/csg-0246_225.jp2/full/,150/0/default/jpg",
            "href": "https://www.e-codices.unifr.ch/en/csg/0246/225",
            "width": 112.5,
            "height": 150,
            "label": "p. 225"
        },
        {
            "id": "155690",
            "src": "https://www.e-codices.unifr.ch/loris/csg/csg-0246/csg-0246_226.jp2/full/,150/0/default/jpg",
            "href": "https://www.e-codices.unifr.ch/en/csg/0246/226",
            "width": 112.5,
            "height": 150,
            "label": "p. 226"
        },
        {
            "id": "155691",
            "src": "https://www.e-codices.unifr.ch/loris/csg/csg-0246/csg-0246_227.jp2/full/,150/0/default/jpg",
            "href": "https://www.e-codices.unifr.ch/en/csg/0246/227",
            "width": 112.5,
            "height": 150,
            "label": "p. 227"
        },
        {
            "id": "155692",
            "src": "https://www.e-codices.unifr.ch/loris/csg/csg-0246/csg-0246_228.jp2/full/,150/0/default/jpg",
            "href": "https://www.e-codices.unifr.ch/en/csg/0246/228",
            "width": 112.5,
            "height": 150,
            "label": "p. 228"
        },
        {
            "id": "155698",
            "src": "https://www.e-codices.unifr.ch/loris/csg/csg-0246/csg-0246_e006.jp2/full/,150/0/default/jpg",
            "href": "https://www.e-codices.unifr.ch/en/csg/0246/bindingF",
            "width": 112.5,
            "height": 150,
            "label": "Rear paste-down"
        },
        {
            "id": "155695",
            "src": "https://www.e-codices.unifr.ch/loris/csg/csg-0246/csg-0246_e003.jp2/full/,150/0/default/jpg",
            "href": "https://www.e-codices.unifr.ch/en/csg/0246/bindingC",
            "width": 112.5,
            "height": 150,
            "label": "Back cover"
        },
        {
            "id": "155694",
            "src": "https://www.e-codices.unifr.ch/loris/csg/csg-0246/csg-0246_e002.jp2/full/,150/0/default/jpg",
            "href": "https://www.e-codices.unifr.ch/en/csg/0246/bindingB",
            "width": 112.5,
            "height": 150,
            "label": "Spine"
        },
        {
            "id": "155696",
            "src": "https://www.e-codices.unifr.ch/loris/csg/csg-0246/csg-0246_e004.jp2/full/,150/0/default/jpg",
            "href": "https://www.e-codices.unifr.ch/en/csg/0246/bindingD",
            "width": 112.5,
            "height": 150,
            "label": "Fore edge"
        },
        {
            "id": "155699",
            "src": "https://www.e-codices.unifr.ch/loris/csg/csg-0246/csg-0246_e007.jp2/full/,150/0/default/jpg",
            "href": "https://www.e-codices.unifr.ch/en/csg/0246/bindingG",
            "width": 112.5,
            "height": 150,
            "label": "Head"
        },
        {
            "id": "155700",
            "src": "https://www.e-codices.unifr.ch/loris/csg/csg-0246/csg-0246_e008.jp2/full/,150/0/default/jpg",
            "href": "https://www.e-codices.unifr.ch/en/csg/0246/bindingH",
            "width": 112.5,
            "height": 150,
            "label": "Tail"
        },
        {
            "id": "155701",
            "src": "https://www.e-codices.unifr.ch/loris/csg/csg-0246/csg-0246_bz.jp2/full/,150/0/default/jpg",
            "href": "https://www.e-codices.unifr.ch/en/csg/0246/bookmark",
            "width": 112.426614481409,
            "height": 150,
            "label": "Bookmark"
        },
        {
            "id": "155702",
            "src": "https://www.e-codices.unifr.ch/loris/csg/csg-0246/csg-0246_MassE.jp2/full/,150/0/default/jpg",
            "href": "https://www.e-codices.unifr.ch/en/csg/0246/bindingRulerE",
            "width": 112.5,
            "height": 150,
            "label": "Ruler on binding"
        },
        {
            "id": "155703",
            "src": "https://www.e-codices.unifr.ch/loris/csg/csg-0246/csg-0246_MassS.jp2/full/,150/0/default/jpg",
            "href": "https://www.e-codices.unifr.ch/en/csg/0246/bindingRulerS",
            "width": 112.5,
            "height": 150,
            "label": "Ruler on page"
        },
        {
            "id": "155704",
            "src": "https://www.e-codices.unifr.ch/loris/csg/csg-0246/csg-0246_ProfilE.jp2/full/,150/0/default/jpg",
            "href": "https://www.e-codices.unifr.ch/en/csg/0246/bindingProfileE",
            "width": 112.5,
            "height": 150,
            "label": "QP card on binding"
        },
        {
            "id": "155705",
            "src": "https://www.e-codices.unifr.ch/loris/csg/csg-0246/csg-0246_ProfilS.jp2/full/,150/0/default/jpg",
            "href": "https://www.e-codices.unifr.ch/en/csg/0246/bindingProfileS",
            "width": 112.5,
            "height": 150,
            "label": "QP card on page"
        },
        {
            "id": "155706",
            "src": "https://www.e-codices.unifr.ch/loris/csg/csg-0246/csg-0246_ProfilSG.jp2/full/,150/0/default/jpg",
            "href": "https://www.e-codices.unifr.ch/en/csg/0246/bindingProfileSG",
            "width": 200,
            "height": 150,
            "label": "Digital Colorchecker"
        }
    ],
    "customViewerBackgroundColor": "#000000"
}