{
    "breadcrumbData": {
        "isVirtualManuscript": false,
        "primaryManuscript": {
            "collection": {
                "label": "St. Gallen, Stiftsbibliothek",
                "url": "https://www.e-codices.unifr.ch/en/search/?iCurrentPage=1&sQueryString=&sSearchField=fullText&sSortField=score&aSelectedFacets[collection_facet][]=St.+Gallen%2C+Stiftsbibliothek"
            },
            "shelfmark": {
                "label": "Cod. Sang. 844",
                "url": "https://www.e-codices.unifr.ch/en/list/one/csg/0844"
            },
            "title": {
                "label": "Boethius, De consolatione philosophiae"
            },
            "page": {
                "label": "Thumbnails"
            }
        }
    },
    "canvases": [
        {
            "id": "243568",
            "src": "https://www.e-codices.unifr.ch/loris/csg/csg-0844/csg-0844_e001.jp2/full/,150/0/default/jpg",
            "href": "https://www.e-codices.unifr.ch/en/csg/0844/bindingA",
            "width": 100,
            "height": 150,
            "label": "Front cover",
            "active": true
        },
        {
            "id": "243572",
            "src": "https://www.e-codices.unifr.ch/loris/csg/csg-0844/csg-0844_e005.jp2/full/,150/0/default/jpg",
            "href": "https://www.e-codices.unifr.ch/en/csg/0844/bindingE",
            "width": 100,
            "height": 150,
            "label": "Front paste-down"
        },
        {
            "id": "243380",
            "src": "https://www.e-codices.unifr.ch/loris/csg/csg-0844/csg-0844_000a.jp2/full/,150/0/default/jpg",
            "href": "https://www.e-codices.unifr.ch/en/csg/0844/V1",
            "width": 100,
            "height": 150,
            "label": "f. V1"
        },
        {
            "id": "243381",
            "src": "https://www.e-codices.unifr.ch/loris/csg/csg-0844/csg-0844_000b.jp2/full/,150/0/default/jpg",
            "href": "https://www.e-codices.unifr.ch/en/csg/0844/V2",
            "width": 100,
            "height": 150,
            "label": "f. V2"
        },
        {
            "id": "243382",
            "src": "https://www.e-codices.unifr.ch/loris/csg/csg-0844/csg-0844_001.jp2/full/,150/0/default/jpg",
            "href": "https://www.e-codices.unifr.ch/en/csg/0844/1",
            "width": 100,
            "height": 150,
            "label": "f. 1"
        },
        {
            "id": "243383",
            "src": "https://www.e-codices.unifr.ch/loris/csg/csg-0844/csg-0844_002.jp2/full/,150/0/default/jpg",
            "href": "https://www.e-codices.unifr.ch/en/csg/0844/2",
            "width": 100,
            "height": 150,
            "label": "f. 2"
        },
        {
            "id": "243384",
            "src": "https://www.e-codices.unifr.ch/loris/csg/csg-0844/csg-0844_003.jp2/full/,150/0/default/jpg",
            "href": "https://www.e-codices.unifr.ch/en/csg/0844/3",
            "width": 100,
            "height": 150,
            "label": "f. 3"
        },
        {
            "id": "243385",
            "src": "https://www.e-codices.unifr.ch/loris/csg/csg-0844/csg-0844_004.jp2/full/,150/0/default/jpg",
            "href": "https://www.e-codices.unifr.ch/en/csg/0844/4",
            "width": 100,
            "height": 150,
            "label": "f. 4"
        },
        {
            "id": "243386",
            "src": "https://www.e-codices.unifr.ch/loris/csg/csg-0844/csg-0844_005.jp2/full/,150/0/default/jpg",
            "href": "https://www.e-codices.unifr.ch/en/csg/0844/5",
            "width": 100,
            "height": 150,
            "label": "f. 5"
        },
        {
            "id": "243387",
            "src": "https://www.e-codices.unifr.ch/loris/csg/csg-0844/csg-0844_006.jp2/full/,150/0/default/jpg",
            "href": "https://www.e-codices.unifr.ch/en/csg/0844/6",
            "width": 100,
            "height": 150,
            "label": "f. 6"
        },
        {
            "id": "243388",
            "src": "https://www.e-codices.unifr.ch/loris/csg/csg-0844/csg-0844_007.jp2/full/,150/0/default/jpg",
            "href": "https://www.e-codices.unifr.ch/en/csg/0844/7",
            "width": 100,
            "height": 150,
            "label": "f. 7"
        },
        {
            "id": "243389",
            "src": "https://www.e-codices.unifr.ch/loris/csg/csg-0844/csg-0844_008.jp2/full/,150/0/default/jpg",
            "href": "https://www.e-codices.unifr.ch/en/csg/0844/8",
            "width": 100,
            "height": 150,
            "label": "f. 8"
        },
        {
            "id": "243390",
            "src": "https://www.e-codices.unifr.ch/loris/csg/csg-0844/csg-0844_009.jp2/full/,150/0/default/jpg",
            "href": "https://www.e-codices.unifr.ch/en/csg/0844/9",
            "width": 100,
            "height": 150,
            "label": "f. 9"
        },
        {
            "id": "243391",
            "src": "https://www.e-codices.unifr.ch/loris/csg/csg-0844/csg-0844_010.jp2/full/,150/0/default/jpg",
            "href": "https://www.e-codices.unifr.ch/en/csg/0844/10",
            "width": 100,
            "height": 150,
            "label": "f. 10"
        },
        {
            "id": "243392",
            "src": "https://www.e-codices.unifr.ch/loris/csg/csg-0844/csg-0844_011.jp2/full/,150/0/default/jpg",
            "href": "https://www.e-codices.unifr.ch/en/csg/0844/11",
            "width": 100,
            "height": 150,
            "label": "f. 11"
        },
        {
            "id": "243393",
            "src": "https://www.e-codices.unifr.ch/loris/csg/csg-0844/csg-0844_012.jp2/full/,150/0/default/jpg",
            "href": "https://www.e-codices.unifr.ch/en/csg/0844/12",
            "width": 100,
            "height": 150,
            "label": "f. 12"
        },
        {
            "id": "243394",
            "src": "https://www.e-codices.unifr.ch/loris/csg/csg-0844/csg-0844_013.jp2/full/,150/0/default/jpg",
            "href": "https://www.e-codices.unifr.ch/en/csg/0844/13",
            "width": 100,
            "height": 150,
            "label": "f. 13"
        },
        {
            "id": "243395",
            "src": "https://www.e-codices.unifr.ch/loris/csg/csg-0844/csg-0844_014.jp2/full/,150/0/default/jpg",
            "href": "https://www.e-codices.unifr.ch/en/csg/0844/14",
            "width": 100,
            "height": 150,
            "label": "f. 14"
        },
        {
            "id": "243396",
            "src": "https://www.e-codices.unifr.ch/loris/csg/csg-0844/csg-0844_015.jp2/full/,150/0/default/jpg",
            "href": "https://www.e-codices.unifr.ch/en/csg/0844/15",
            "width": 100,
            "height": 150,
            "label": "f. 15"
        },
        {
            "id": "243397",
            "src": "https://www.e-codices.unifr.ch/loris/csg/csg-0844/csg-0844_016.jp2/full/,150/0/default/jpg",
            "href": "https://www.e-codices.unifr.ch/en/csg/0844/16",
            "width": 100,
            "height": 150,
            "label": "f. 16"
        },
        {
            "id": "243398",
            "src": "https://www.e-codices.unifr.ch/loris/csg/csg-0844/csg-0844_017.jp2/full/,150/0/default/jpg",
            "href": "https://www.e-codices.unifr.ch/en/csg/0844/17",
            "width": 100,
            "height": 150,
            "label": "f. 17"
        },
        {
            "id": "243399",
            "src": "https://www.e-codices.unifr.ch/loris/csg/csg-0844/csg-0844_018.jp2/full/,150/0/default/jpg",
            "href": "https://www.e-codices.unifr.ch/en/csg/0844/18",
            "width": 100,
            "height": 150,
            "label": "f. 18"
        },
        {
            "id": "243400",
            "src": "https://www.e-codices.unifr.ch/loris/csg/csg-0844/csg-0844_019.jp2/full/,150/0/default/jpg",
            "href": "https://www.e-codices.unifr.ch/en/csg/0844/19",
            "width": 100,
            "height": 150,
            "label": "f. 19"
        },
        {
            "id": "243401",
            "src": "https://www.e-codices.unifr.ch/loris/csg/csg-0844/csg-0844_020.jp2/full/,150/0/default/jpg",
            "href": "https://www.e-codices.unifr.ch/en/csg/0844/20",
            "width": 100,
            "height": 150,
            "label": "f. 20"
        },
        {
            "id": "243402",
            "src": "https://www.e-codices.unifr.ch/loris/csg/csg-0844/csg-0844_021.jp2/full/,150/0/default/jpg",
            "href": "https://www.e-codices.unifr.ch/en/csg/0844/21",
            "width": 100,
            "height": 150,
            "label": "f. 21"
        },
        {
            "id": "243403",
            "src": "https://www.e-codices.unifr.ch/loris/csg/csg-0844/csg-0844_022.jp2/full/,150/0/default/jpg",
            "href": "https://www.e-codices.unifr.ch/en/csg/0844/22",
            "width": 100,
            "height": 150,
            "label": "f. 22"
        },
        {
            "id": "243404",
            "src": "https://www.e-codices.unifr.ch/loris/csg/csg-0844/csg-0844_023.jp2/full/,150/0/default/jpg",
            "href": "https://www.e-codices.unifr.ch/en/csg/0844/23",
            "width": 100,
            "height": 150,
            "label": "f. 23"
        },
        {
            "id": "243405",
            "src": "https://www.e-codices.unifr.ch/loris/csg/csg-0844/csg-0844_024.jp2/full/,150/0/default/jpg",
            "href": "https://www.e-codices.unifr.ch/en/csg/0844/24",
            "width": 100,
            "height": 150,
            "label": "f. 24"
        },
        {
            "id": "243406",
            "src": "https://www.e-codices.unifr.ch/loris/csg/csg-0844/csg-0844_025.jp2/full/,150/0/default/jpg",
            "href": "https://www.e-codices.unifr.ch/en/csg/0844/25",
            "width": 100,
            "height": 150,
            "label": "f. 25"
        },
        {
            "id": "243407",
            "src": "https://www.e-codices.unifr.ch/loris/csg/csg-0844/csg-0844_026.jp2/full/,150/0/default/jpg",
            "href": "https://www.e-codices.unifr.ch/en/csg/0844/26",
            "width": 100,
            "height": 150,
            "label": "f. 26"
        },
        {
            "id": "243408",
            "src": "https://www.e-codices.unifr.ch/loris/csg/csg-0844/csg-0844_027.jp2/full/,150/0/default/jpg",
            "href": "https://www.e-codices.unifr.ch/en/csg/0844/27",
            "width": 100,
            "height": 150,
            "label": "f. 27"
        },
        {
            "id": "243409",
            "src": "https://www.e-codices.unifr.ch/loris/csg/csg-0844/csg-0844_028.jp2/full/,150/0/default/jpg",
            "href": "https://www.e-codices.unifr.ch/en/csg/0844/28",
            "width": 100,
            "height": 150,
            "label": "f. 28"
        },
        {
            "id": "243410",
            "src": "https://www.e-codices.unifr.ch/loris/csg/csg-0844/csg-0844_029.jp2/full/,150/0/default/jpg",
            "href": "https://www.e-codices.unifr.ch/en/csg/0844/29",
            "width": 100,
            "height": 150,
            "label": "f. 29"
        },
        {
            "id": "243411",
            "src": "https://www.e-codices.unifr.ch/loris/csg/csg-0844/csg-0844_030.jp2/full/,150/0/default/jpg",
            "href": "https://www.e-codices.unifr.ch/en/csg/0844/30",
            "width": 100,
            "height": 150,
            "label": "f. 30"
        },
        {
            "id": "243412",
            "src": "https://www.e-codices.unifr.ch/loris/csg/csg-0844/csg-0844_031.jp2/full/,150/0/default/jpg",
            "href": "https://www.e-codices.unifr.ch/en/csg/0844/31",
            "width": 100,
            "height": 150,
            "label": "f. 31"
        },
        {
            "id": "243413",
            "src": "https://www.e-codices.unifr.ch/loris/csg/csg-0844/csg-0844_032.jp2/full/,150/0/default/jpg",
            "href": "https://www.e-codices.unifr.ch/en/csg/0844/32",
            "width": 100,
            "height": 150,
            "label": "f. 32"
        },
        {
            "id": "243414",
            "src": "https://www.e-codices.unifr.ch/loris/csg/csg-0844/csg-0844_033.jp2/full/,150/0/default/jpg",
            "href": "https://www.e-codices.unifr.ch/en/csg/0844/33",
            "width": 100,
            "height": 150,
            "label": "f. 33"
        },
        {
            "id": "243415",
            "src": "https://www.e-codices.unifr.ch/loris/csg/csg-0844/csg-0844_034.jp2/full/,150/0/default/jpg",
            "href": "https://www.e-codices.unifr.ch/en/csg/0844/34",
            "width": 100,
            "height": 150,
            "label": "f. 34"
        },
        {
            "id": "243416",
            "src": "https://www.e-codices.unifr.ch/loris/csg/csg-0844/csg-0844_035.jp2/full/,150/0/default/jpg",
            "href": "https://www.e-codices.unifr.ch/en/csg/0844/35",
            "width": 100,
            "height": 150,
            "label": "f. 35"
        },
        {
            "id": "243417",
            "src": "https://www.e-codices.unifr.ch/loris/csg/csg-0844/csg-0844_036.jp2/full/,150/0/default/jpg",
            "href": "https://www.e-codices.unifr.ch/en/csg/0844/36",
            "width": 100,
            "height": 150,
            "label": "f. 36"
        },
        {
            "id": "243418",
            "src": "https://www.e-codices.unifr.ch/loris/csg/csg-0844/csg-0844_037.jp2/full/,150/0/default/jpg",
            "href": "https://www.e-codices.unifr.ch/en/csg/0844/37",
            "width": 100,
            "height": 150,
            "label": "f. 37"
        },
        {
            "id": "243419",
            "src": "https://www.e-codices.unifr.ch/loris/csg/csg-0844/csg-0844_038.jp2/full/,150/0/default/jpg",
            "href": "https://www.e-codices.unifr.ch/en/csg/0844/38",
            "width": 100,
            "height": 150,
            "label": "f. 38"
        },
        {
            "id": "243420",
            "src": "https://www.e-codices.unifr.ch/loris/csg/csg-0844/csg-0844_039.jp2/full/,150/0/default/jpg",
            "href": "https://www.e-codices.unifr.ch/en/csg/0844/39",
            "width": 100,
            "height": 150,
            "label": "f. 39"
        },
        {
            "id": "243421",
            "src": "https://www.e-codices.unifr.ch/loris/csg/csg-0844/csg-0844_040.jp2/full/,150/0/default/jpg",
            "href": "https://www.e-codices.unifr.ch/en/csg/0844/40",
            "width": 100,
            "height": 150,
            "label": "f. 40"
        },
        {
            "id": "243422",
            "src": "https://www.e-codices.unifr.ch/loris/csg/csg-0844/csg-0844_041.jp2/full/,150/0/default/jpg",
            "href": "https://www.e-codices.unifr.ch/en/csg/0844/41",
            "width": 100,
            "height": 150,
            "label": "f. 41"
        },
        {
            "id": "243423",
            "src": "https://www.e-codices.unifr.ch/loris/csg/csg-0844/csg-0844_042.jp2/full/,150/0/default/jpg",
            "href": "https://www.e-codices.unifr.ch/en/csg/0844/42",
            "width": 100,
            "height": 150,
            "label": "f. 42"
        },
        {
            "id": "243424",
            "src": "https://www.e-codices.unifr.ch/loris/csg/csg-0844/csg-0844_043.jp2/full/,150/0/default/jpg",
            "href": "https://www.e-codices.unifr.ch/en/csg/0844/43",
            "width": 100,
            "height": 150,
            "label": "f. 43"
        },
        {
            "id": "243425",
            "src": "https://www.e-codices.unifr.ch/loris/csg/csg-0844/csg-0844_044.jp2/full/,150/0/default/jpg",
            "href": "https://www.e-codices.unifr.ch/en/csg/0844/44",
            "width": 100,
            "height": 150,
            "label": "f. 44"
        },
        {
            "id": "243426",
            "src": "https://www.e-codices.unifr.ch/loris/csg/csg-0844/csg-0844_045.jp2/full/,150/0/default/jpg",
            "href": "https://www.e-codices.unifr.ch/en/csg/0844/45",
            "width": 100,
            "height": 150,
            "label": "f. 45"
        },
        {
            "id": "243427",
            "src": "https://www.e-codices.unifr.ch/loris/csg/csg-0844/csg-0844_046.jp2/full/,150/0/default/jpg",
            "href": "https://www.e-codices.unifr.ch/en/csg/0844/46",
            "width": 100,
            "height": 150,
            "label": "f. 46"
        },
        {
            "id": "243428",
            "src": "https://www.e-codices.unifr.ch/loris/csg/csg-0844/csg-0844_047.jp2/full/,150/0/default/jpg",
            "href": "https://www.e-codices.unifr.ch/en/csg/0844/47",
            "width": 100,
            "height": 150,
            "label": "f. 47"
        },
        {
            "id": "243429",
            "src": "https://www.e-codices.unifr.ch/loris/csg/csg-0844/csg-0844_048.jp2/full/,150/0/default/jpg",
            "href": "https://www.e-codices.unifr.ch/en/csg/0844/48",
            "width": 100,
            "height": 150,
            "label": "f. 48"
        },
        {
            "id": "243430",
            "src": "https://www.e-codices.unifr.ch/loris/csg/csg-0844/csg-0844_049.jp2/full/,150/0/default/jpg",
            "href": "https://www.e-codices.unifr.ch/en/csg/0844/49",
            "width": 100,
            "height": 150,
            "label": "f. 49"
        },
        {
            "id": "243431",
            "src": "https://www.e-codices.unifr.ch/loris/csg/csg-0844/csg-0844_050.jp2/full/,150/0/default/jpg",
            "href": "https://www.e-codices.unifr.ch/en/csg/0844/50",
            "width": 100,
            "height": 150,
            "label": "f. 50"
        },
        {
            "id": "243432",
            "src": "https://www.e-codices.unifr.ch/loris/csg/csg-0844/csg-0844_051.jp2/full/,150/0/default/jpg",
            "href": "https://www.e-codices.unifr.ch/en/csg/0844/51",
            "width": 100,
            "height": 150,
            "label": "f. 51"
        },
        {
            "id": "243433",
            "src": "https://www.e-codices.unifr.ch/loris/csg/csg-0844/csg-0844_052.jp2/full/,150/0/default/jpg",
            "href": "https://www.e-codices.unifr.ch/en/csg/0844/52",
            "width": 100,
            "height": 150,
            "label": "f. 52"
        },
        {
            "id": "243434",
            "src": "https://www.e-codices.unifr.ch/loris/csg/csg-0844/csg-0844_053.jp2/full/,150/0/default/jpg",
            "href": "https://www.e-codices.unifr.ch/en/csg/0844/53",
            "width": 100,
            "height": 150,
            "label": "f. 53"
        },
        {
            "id": "243435",
            "src": "https://www.e-codices.unifr.ch/loris/csg/csg-0844/csg-0844_054.jp2/full/,150/0/default/jpg",
            "href": "https://www.e-codices.unifr.ch/en/csg/0844/54",
            "width": 100,
            "height": 150,
            "label": "f. 54"
        },
        {
            "id": "243436",
            "src": "https://www.e-codices.unifr.ch/loris/csg/csg-0844/csg-0844_055.jp2/full/,150/0/default/jpg",
            "href": "https://www.e-codices.unifr.ch/en/csg/0844/55",
            "width": 100,
            "height": 150,
            "label": "f. 55"
        },
        {
            "id": "243437",
            "src": "https://www.e-codices.unifr.ch/loris/csg/csg-0844/csg-0844_056.jp2/full/,150/0/default/jpg",
            "href": "https://www.e-codices.unifr.ch/en/csg/0844/56",
            "width": 100,
            "height": 150,
            "label": "f. 56"
        },
        {
            "id": "243438",
            "src": "https://www.e-codices.unifr.ch/loris/csg/csg-0844/csg-0844_057.jp2/full/,150/0/default/jpg",
            "href": "https://www.e-codices.unifr.ch/en/csg/0844/57",
            "width": 100,
            "height": 150,
            "label": "f. 57"
        },
        {
            "id": "243439",
            "src": "https://www.e-codices.unifr.ch/loris/csg/csg-0844/csg-0844_058.jp2/full/,150/0/default/jpg",
            "href": "https://www.e-codices.unifr.ch/en/csg/0844/58",
            "width": 100,
            "height": 150,
            "label": "f. 58"
        },
        {
            "id": "243440",
            "src": "https://www.e-codices.unifr.ch/loris/csg/csg-0844/csg-0844_059.jp2/full/,150/0/default/jpg",
            "href": "https://www.e-codices.unifr.ch/en/csg/0844/59",
            "width": 100,
            "height": 150,
            "label": "f. 59"
        },
        {
            "id": "243441",
            "src": "https://www.e-codices.unifr.ch/loris/csg/csg-0844/csg-0844_060.jp2/full/,150/0/default/jpg",
            "href": "https://www.e-codices.unifr.ch/en/csg/0844/60",
            "width": 100,
            "height": 150,
            "label": "f. 60"
        },
        {
            "id": "243442",
            "src": "https://www.e-codices.unifr.ch/loris/csg/csg-0844/csg-0844_061.jp2/full/,150/0/default/jpg",
            "href": "https://www.e-codices.unifr.ch/en/csg/0844/61",
            "width": 100,
            "height": 150,
            "label": "f. 61"
        },
        {
            "id": "243443",
            "src": "https://www.e-codices.unifr.ch/loris/csg/csg-0844/csg-0844_062.jp2/full/,150/0/default/jpg",
            "href": "https://www.e-codices.unifr.ch/en/csg/0844/62",
            "width": 100,
            "height": 150,
            "label": "f. 62"
        },
        {
            "id": "243444",
            "src": "https://www.e-codices.unifr.ch/loris/csg/csg-0844/csg-0844_063.jp2/full/,150/0/default/jpg",
            "href": "https://www.e-codices.unifr.ch/en/csg/0844/63",
            "width": 100,
            "height": 150,
            "label": "f. 63"
        },
        {
            "id": "243445",
            "src": "https://www.e-codices.unifr.ch/loris/csg/csg-0844/csg-0844_064.jp2/full/,150/0/default/jpg",
            "href": "https://www.e-codices.unifr.ch/en/csg/0844/64",
            "width": 100,
            "height": 150,
            "label": "f. 64"
        },
        {
            "id": "243446",
            "src": "https://www.e-codices.unifr.ch/loris/csg/csg-0844/csg-0844_065.jp2/full/,150/0/default/jpg",
            "href": "https://www.e-codices.unifr.ch/en/csg/0844/65",
            "width": 100,
            "height": 150,
            "label": "f. 65"
        },
        {
            "id": "243447",
            "src": "https://www.e-codices.unifr.ch/loris/csg/csg-0844/csg-0844_066.jp2/full/,150/0/default/jpg",
            "href": "https://www.e-codices.unifr.ch/en/csg/0844/66",
            "width": 100,
            "height": 150,
            "label": "f. 66"
        },
        {
            "id": "243448",
            "src": "https://www.e-codices.unifr.ch/loris/csg/csg-0844/csg-0844_067.jp2/full/,150/0/default/jpg",
            "href": "https://www.e-codices.unifr.ch/en/csg/0844/67",
            "width": 100,
            "height": 150,
            "label": "f. 67"
        },
        {
            "id": "243449",
            "src": "https://www.e-codices.unifr.ch/loris/csg/csg-0844/csg-0844_068.jp2/full/,150/0/default/jpg",
            "href": "https://www.e-codices.unifr.ch/en/csg/0844/68",
            "width": 100,
            "height": 150,
            "label": "f. 68"
        },
        {
            "id": "243450",
            "src": "https://www.e-codices.unifr.ch/loris/csg/csg-0844/csg-0844_069.jp2/full/,150/0/default/jpg",
            "href": "https://www.e-codices.unifr.ch/en/csg/0844/69",
            "width": 100,
            "height": 150,
            "label": "f. 69"
        },
        {
            "id": "243451",
            "src": "https://www.e-codices.unifr.ch/loris/csg/csg-0844/csg-0844_070.jp2/full/,150/0/default/jpg",
            "href": "https://www.e-codices.unifr.ch/en/csg/0844/70",
            "width": 100,
            "height": 150,
            "label": "f. 70"
        },
        {
            "id": "243452",
            "src": "https://www.e-codices.unifr.ch/loris/csg/csg-0844/csg-0844_071.jp2/full/,150/0/default/jpg",
            "href": "https://www.e-codices.unifr.ch/en/csg/0844/71",
            "width": 100,
            "height": 150,
            "label": "f. 71"
        },
        {
            "id": "243453",
            "src": "https://www.e-codices.unifr.ch/loris/csg/csg-0844/csg-0844_072.jp2/full/,150/0/default/jpg",
            "href": "https://www.e-codices.unifr.ch/en/csg/0844/72",
            "width": 100,
            "height": 150,
            "label": "f. 72"
        },
        {
            "id": "243454",
            "src": "https://www.e-codices.unifr.ch/loris/csg/csg-0844/csg-0844_073.jp2/full/,150/0/default/jpg",
            "href": "https://www.e-codices.unifr.ch/en/csg/0844/73",
            "width": 100,
            "height": 150,
            "label": "f. 73"
        },
        {
            "id": "243455",
            "src": "https://www.e-codices.unifr.ch/loris/csg/csg-0844/csg-0844_074.jp2/full/,150/0/default/jpg",
            "href": "https://www.e-codices.unifr.ch/en/csg/0844/74",
            "width": 100,
            "height": 150,
            "label": "f. 74"
        },
        {
            "id": "243456",
            "src": "https://www.e-codices.unifr.ch/loris/csg/csg-0844/csg-0844_075.jp2/full/,150/0/default/jpg",
            "href": "https://www.e-codices.unifr.ch/en/csg/0844/75",
            "width": 100,
            "height": 150,
            "label": "f. 75"
        },
        {
            "id": "243457",
            "src": "https://www.e-codices.unifr.ch/loris/csg/csg-0844/csg-0844_076.jp2/full/,150/0/default/jpg",
            "href": "https://www.e-codices.unifr.ch/en/csg/0844/76",
            "width": 100,
            "height": 150,
            "label": "f. 76"
        },
        {
            "id": "243458",
            "src": "https://www.e-codices.unifr.ch/loris/csg/csg-0844/csg-0844_077.jp2/full/,150/0/default/jpg",
            "href": "https://www.e-codices.unifr.ch/en/csg/0844/77",
            "width": 100,
            "height": 150,
            "label": "f. 77"
        },
        {
            "id": "243459",
            "src": "https://www.e-codices.unifr.ch/loris/csg/csg-0844/csg-0844_078.jp2/full/,150/0/default/jpg",
            "href": "https://www.e-codices.unifr.ch/en/csg/0844/78",
            "width": 100,
            "height": 150,
            "label": "f. 78"
        },
        {
            "id": "243460",
            "src": "https://www.e-codices.unifr.ch/loris/csg/csg-0844/csg-0844_079.jp2/full/,150/0/default/jpg",
            "href": "https://www.e-codices.unifr.ch/en/csg/0844/79",
            "width": 100,
            "height": 150,
            "label": "f. 79"
        },
        {
            "id": "243461",
            "src": "https://www.e-codices.unifr.ch/loris/csg/csg-0844/csg-0844_080.jp2/full/,150/0/default/jpg",
            "href": "https://www.e-codices.unifr.ch/en/csg/0844/80",
            "width": 100,
            "height": 150,
            "label": "f. 80"
        },
        {
            "id": "243462",
            "src": "https://www.e-codices.unifr.ch/loris/csg/csg-0844/csg-0844_081.jp2/full/,150/0/default/jpg",
            "href": "https://www.e-codices.unifr.ch/en/csg/0844/81",
            "width": 100,
            "height": 150,
            "label": "f. 81"
        },
        {
            "id": "243463",
            "src": "https://www.e-codices.unifr.ch/loris/csg/csg-0844/csg-0844_082.jp2/full/,150/0/default/jpg",
            "href": "https://www.e-codices.unifr.ch/en/csg/0844/82",
            "width": 100,
            "height": 150,
            "label": "f. 82"
        },
        {
            "id": "243464",
            "src": "https://www.e-codices.unifr.ch/loris/csg/csg-0844/csg-0844_083.jp2/full/,150/0/default/jpg",
            "href": "https://www.e-codices.unifr.ch/en/csg/0844/83",
            "width": 100,
            "height": 150,
            "label": "f. 83"
        },
        {
            "id": "243465",
            "src": "https://www.e-codices.unifr.ch/loris/csg/csg-0844/csg-0844_084.jp2/full/,150/0/default/jpg",
            "href": "https://www.e-codices.unifr.ch/en/csg/0844/84",
            "width": 100,
            "height": 150,
            "label": "f. 84"
        },
        {
            "id": "243466",
            "src": "https://www.e-codices.unifr.ch/loris/csg/csg-0844/csg-0844_085.jp2/full/,150/0/default/jpg",
            "href": "https://www.e-codices.unifr.ch/en/csg/0844/85",
            "width": 100,
            "height": 150,
            "label": "f. 85"
        },
        {
            "id": "243467",
            "src": "https://www.e-codices.unifr.ch/loris/csg/csg-0844/csg-0844_086.jp2/full/,150/0/default/jpg",
            "href": "https://www.e-codices.unifr.ch/en/csg/0844/86",
            "width": 100,
            "height": 150,
            "label": "f. 86"
        },
        {
            "id": "243468",
            "src": "https://www.e-codices.unifr.ch/loris/csg/csg-0844/csg-0844_087.jp2/full/,150/0/default/jpg",
            "href": "https://www.e-codices.unifr.ch/en/csg/0844/87",
            "width": 100,
            "height": 150,
            "label": "f. 87"
        },
        {
            "id": "243469",
            "src": "https://www.e-codices.unifr.ch/loris/csg/csg-0844/csg-0844_088.jp2/full/,150/0/default/jpg",
            "href": "https://www.e-codices.unifr.ch/en/csg/0844/88",
            "width": 100,
            "height": 150,
            "label": "f. 88"
        },
        {
            "id": "243470",
            "src": "https://www.e-codices.unifr.ch/loris/csg/csg-0844/csg-0844_089.jp2/full/,150/0/default/jpg",
            "href": "https://www.e-codices.unifr.ch/en/csg/0844/89",
            "width": 100,
            "height": 150,
            "label": "f. 89"
        },
        {
            "id": "243471",
            "src": "https://www.e-codices.unifr.ch/loris/csg/csg-0844/csg-0844_090.jp2/full/,150/0/default/jpg",
            "href": "https://www.e-codices.unifr.ch/en/csg/0844/90",
            "width": 100,
            "height": 150,
            "label": "f. 90"
        },
        {
            "id": "243472",
            "src": "https://www.e-codices.unifr.ch/loris/csg/csg-0844/csg-0844_091.jp2/full/,150/0/default/jpg",
            "href": "https://www.e-codices.unifr.ch/en/csg/0844/91",
            "width": 100,
            "height": 150,
            "label": "f. 91"
        },
        {
            "id": "243473",
            "src": "https://www.e-codices.unifr.ch/loris/csg/csg-0844/csg-0844_092.jp2/full/,150/0/default/jpg",
            "href": "https://www.e-codices.unifr.ch/en/csg/0844/92",
            "width": 100,
            "height": 150,
            "label": "f. 92"
        },
        {
            "id": "243474",
            "src": "https://www.e-codices.unifr.ch/loris/csg/csg-0844/csg-0844_093.jp2/full/,150/0/default/jpg",
            "href": "https://www.e-codices.unifr.ch/en/csg/0844/93",
            "width": 100,
            "height": 150,
            "label": "f. 93"
        },
        {
            "id": "243475",
            "src": "https://www.e-codices.unifr.ch/loris/csg/csg-0844/csg-0844_094.jp2/full/,150/0/default/jpg",
            "href": "https://www.e-codices.unifr.ch/en/csg/0844/94",
            "width": 100,
            "height": 150,
            "label": "f. 94"
        },
        {
            "id": "243476",
            "src": "https://www.e-codices.unifr.ch/loris/csg/csg-0844/csg-0844_095.jp2/full/,150/0/default/jpg",
            "href": "https://www.e-codices.unifr.ch/en/csg/0844/95",
            "width": 100,
            "height": 150,
            "label": "f. 95"
        },
        {
            "id": "243477",
            "src": "https://www.e-codices.unifr.ch/loris/csg/csg-0844/csg-0844_096.jp2/full/,150/0/default/jpg",
            "href": "https://www.e-codices.unifr.ch/en/csg/0844/96",
            "width": 100,
            "height": 150,
            "label": "f. 96"
        },
        {
            "id": "243478",
            "src": "https://www.e-codices.unifr.ch/loris/csg/csg-0844/csg-0844_097.jp2/full/,150/0/default/jpg",
            "href": "https://www.e-codices.unifr.ch/en/csg/0844/97",
            "width": 100,
            "height": 150,
            "label": "f. 97"
        },
        {
            "id": "243479",
            "src": "https://www.e-codices.unifr.ch/loris/csg/csg-0844/csg-0844_098.jp2/full/,150/0/default/jpg",
            "href": "https://www.e-codices.unifr.ch/en/csg/0844/98",
            "width": 100,
            "height": 150,
            "label": "f. 98"
        },
        {
            "id": "243480",
            "src": "https://www.e-codices.unifr.ch/loris/csg/csg-0844/csg-0844_099.jp2/full/,150/0/default/jpg",
            "href": "https://www.e-codices.unifr.ch/en/csg/0844/99",
            "width": 100,
            "height": 150,
            "label": "f. 99"
        },
        {
            "id": "243481",
            "src": "https://www.e-codices.unifr.ch/loris/csg/csg-0844/csg-0844_100.jp2/full/,150/0/default/jpg",
            "href": "https://www.e-codices.unifr.ch/en/csg/0844/100",
            "width": 100,
            "height": 150,
            "label": "f. 100"
        },
        {
            "id": "243482",
            "src": "https://www.e-codices.unifr.ch/loris/csg/csg-0844/csg-0844_101.jp2/full/,150/0/default/jpg",
            "href": "https://www.e-codices.unifr.ch/en/csg/0844/101",
            "width": 100,
            "height": 150,
            "label": "f. 101"
        },
        {
            "id": "243483",
            "src": "https://www.e-codices.unifr.ch/loris/csg/csg-0844/csg-0844_102.jp2/full/,150/0/default/jpg",
            "href": "https://www.e-codices.unifr.ch/en/csg/0844/102",
            "width": 100,
            "height": 150,
            "label": "f. 102"
        },
        {
            "id": "243484",
            "src": "https://www.e-codices.unifr.ch/loris/csg/csg-0844/csg-0844_103.jp2/full/,150/0/default/jpg",
            "href": "https://www.e-codices.unifr.ch/en/csg/0844/103",
            "width": 100,
            "height": 150,
            "label": "f. 103"
        },
        {
            "id": "243485",
            "src": "https://www.e-codices.unifr.ch/loris/csg/csg-0844/csg-0844_104.jp2/full/,150/0/default/jpg",
            "href": "https://www.e-codices.unifr.ch/en/csg/0844/104",
            "width": 100,
            "height": 150,
            "label": "f. 104"
        },
        {
            "id": "243486",
            "src": "https://www.e-codices.unifr.ch/loris/csg/csg-0844/csg-0844_105.jp2/full/,150/0/default/jpg",
            "href": "https://www.e-codices.unifr.ch/en/csg/0844/105",
            "width": 100,
            "height": 150,
            "label": "f. 105"
        },
        {
            "id": "243487",
            "src": "https://www.e-codices.unifr.ch/loris/csg/csg-0844/csg-0844_106.jp2/full/,150/0/default/jpg",
            "href": "https://www.e-codices.unifr.ch/en/csg/0844/106",
            "width": 100,
            "height": 150,
            "label": "f. 106"
        },
        {
            "id": "243488",
            "src": "https://www.e-codices.unifr.ch/loris/csg/csg-0844/csg-0844_107.jp2/full/,150/0/default/jpg",
            "href": "https://www.e-codices.unifr.ch/en/csg/0844/107",
            "width": 100,
            "height": 150,
            "label": "f. 107"
        },
        {
            "id": "243489",
            "src": "https://www.e-codices.unifr.ch/loris/csg/csg-0844/csg-0844_108.jp2/full/,150/0/default/jpg",
            "href": "https://www.e-codices.unifr.ch/en/csg/0844/108",
            "width": 100,
            "height": 150,
            "label": "f. 108"
        },
        {
            "id": "243490",
            "src": "https://www.e-codices.unifr.ch/loris/csg/csg-0844/csg-0844_109.jp2/full/,150/0/default/jpg",
            "href": "https://www.e-codices.unifr.ch/en/csg/0844/109",
            "width": 100,
            "height": 150,
            "label": "f. 109"
        },
        {
            "id": "243491",
            "src": "https://www.e-codices.unifr.ch/loris/csg/csg-0844/csg-0844_110.jp2/full/,150/0/default/jpg",
            "href": "https://www.e-codices.unifr.ch/en/csg/0844/110",
            "width": 100,
            "height": 150,
            "label": "f. 110"
        },
        {
            "id": "243492",
            "src": "https://www.e-codices.unifr.ch/loris/csg/csg-0844/csg-0844_111.jp2/full/,150/0/default/jpg",
            "href": "https://www.e-codices.unifr.ch/en/csg/0844/111",
            "width": 100,
            "height": 150,
            "label": "f. 111"
        },
        {
            "id": "243493",
            "src": "https://www.e-codices.unifr.ch/loris/csg/csg-0844/csg-0844_112.jp2/full/,150/0/default/jpg",
            "href": "https://www.e-codices.unifr.ch/en/csg/0844/112",
            "width": 100,
            "height": 150,
            "label": "f. 112"
        },
        {
            "id": "243494",
            "src": "https://www.e-codices.unifr.ch/loris/csg/csg-0844/csg-0844_113.jp2/full/,150/0/default/jpg",
            "href": "https://www.e-codices.unifr.ch/en/csg/0844/113",
            "width": 100,
            "height": 150,
            "label": "f. 113"
        },
        {
            "id": "243495",
            "src": "https://www.e-codices.unifr.ch/loris/csg/csg-0844/csg-0844_114.jp2/full/,150/0/default/jpg",
            "href": "https://www.e-codices.unifr.ch/en/csg/0844/114",
            "width": 100,
            "height": 150,
            "label": "f. 114"
        },
        {
            "id": "243496",
            "src": "https://www.e-codices.unifr.ch/loris/csg/csg-0844/csg-0844_115.jp2/full/,150/0/default/jpg",
            "href": "https://www.e-codices.unifr.ch/en/csg/0844/115",
            "width": 100,
            "height": 150,
            "label": "f. 115"
        },
        {
            "id": "243497",
            "src": "https://www.e-codices.unifr.ch/loris/csg/csg-0844/csg-0844_116.jp2/full/,150/0/default/jpg",
            "href": "https://www.e-codices.unifr.ch/en/csg/0844/116",
            "width": 100,
            "height": 150,
            "label": "f. 116"
        },
        {
            "id": "243498",
            "src": "https://www.e-codices.unifr.ch/loris/csg/csg-0844/csg-0844_117.jp2/full/,150/0/default/jpg",
            "href": "https://www.e-codices.unifr.ch/en/csg/0844/117",
            "width": 100,
            "height": 150,
            "label": "f. 117"
        },
        {
            "id": "243499",
            "src": "https://www.e-codices.unifr.ch/loris/csg/csg-0844/csg-0844_118.jp2/full/,150/0/default/jpg",
            "href": "https://www.e-codices.unifr.ch/en/csg/0844/118",
            "width": 100,
            "height": 150,
            "label": "f. 118"
        },
        {
            "id": "243500",
            "src": "https://www.e-codices.unifr.ch/loris/csg/csg-0844/csg-0844_119.jp2/full/,150/0/default/jpg",
            "href": "https://www.e-codices.unifr.ch/en/csg/0844/119",
            "width": 100,
            "height": 150,
            "label": "f. 119"
        },
        {
            "id": "243501",
            "src": "https://www.e-codices.unifr.ch/loris/csg/csg-0844/csg-0844_120.jp2/full/,150/0/default/jpg",
            "href": "https://www.e-codices.unifr.ch/en/csg/0844/120",
            "width": 100,
            "height": 150,
            "label": "f. 120"
        },
        {
            "id": "243502",
            "src": "https://www.e-codices.unifr.ch/loris/csg/csg-0844/csg-0844_121.jp2/full/,150/0/default/jpg",
            "href": "https://www.e-codices.unifr.ch/en/csg/0844/121",
            "width": 100,
            "height": 150,
            "label": "f. 121"
        },
        {
            "id": "243503",
            "src": "https://www.e-codices.unifr.ch/loris/csg/csg-0844/csg-0844_122.jp2/full/,150/0/default/jpg",
            "href": "https://www.e-codices.unifr.ch/en/csg/0844/122",
            "width": 100,
            "height": 150,
            "label": "f. 122"
        },
        {
            "id": "243504",
            "src": "https://www.e-codices.unifr.ch/loris/csg/csg-0844/csg-0844_123.jp2/full/,150/0/default/jpg",
            "href": "https://www.e-codices.unifr.ch/en/csg/0844/123",
            "width": 100,
            "height": 150,
            "label": "f. 123"
        },
        {
            "id": "243505",
            "src": "https://www.e-codices.unifr.ch/loris/csg/csg-0844/csg-0844_124.jp2/full/,150/0/default/jpg",
            "href": "https://www.e-codices.unifr.ch/en/csg/0844/124",
            "width": 100,
            "height": 150,
            "label": "f. 124"
        },
        {
            "id": "243506",
            "src": "https://www.e-codices.unifr.ch/loris/csg/csg-0844/csg-0844_125.jp2/full/,150/0/default/jpg",
            "href": "https://www.e-codices.unifr.ch/en/csg/0844/125",
            "width": 100,
            "height": 150,
            "label": "f. 125"
        },
        {
            "id": "243507",
            "src": "https://www.e-codices.unifr.ch/loris/csg/csg-0844/csg-0844_126.jp2/full/,150/0/default/jpg",
            "href": "https://www.e-codices.unifr.ch/en/csg/0844/126",
            "width": 100,
            "height": 150,
            "label": "f. 126"
        },
        {
            "id": "243508",
            "src": "https://www.e-codices.unifr.ch/loris/csg/csg-0844/csg-0844_127.jp2/full/,150/0/default/jpg",
            "href": "https://www.e-codices.unifr.ch/en/csg/0844/127",
            "width": 100,
            "height": 150,
            "label": "f. 127"
        },
        {
            "id": "243509",
            "src": "https://www.e-codices.unifr.ch/loris/csg/csg-0844/csg-0844_128.jp2/full/,150/0/default/jpg",
            "href": "https://www.e-codices.unifr.ch/en/csg/0844/128",
            "width": 100,
            "height": 150,
            "label": "f. 128"
        },
        {
            "id": "243510",
            "src": "https://www.e-codices.unifr.ch/loris/csg/csg-0844/csg-0844_129.jp2/full/,150/0/default/jpg",
            "href": "https://www.e-codices.unifr.ch/en/csg/0844/129",
            "width": 100,
            "height": 150,
            "label": "f. 129"
        },
        {
            "id": "243511",
            "src": "https://www.e-codices.unifr.ch/loris/csg/csg-0844/csg-0844_130.jp2/full/,150/0/default/jpg",
            "href": "https://www.e-codices.unifr.ch/en/csg/0844/130",
            "width": 100,
            "height": 150,
            "label": "f. 130"
        },
        {
            "id": "243512",
            "src": "https://www.e-codices.unifr.ch/loris/csg/csg-0844/csg-0844_131.jp2/full/,150/0/default/jpg",
            "href": "https://www.e-codices.unifr.ch/en/csg/0844/131",
            "width": 100,
            "height": 150,
            "label": "f. 131"
        },
        {
            "id": "243513",
            "src": "https://www.e-codices.unifr.ch/loris/csg/csg-0844/csg-0844_132.jp2/full/,150/0/default/jpg",
            "href": "https://www.e-codices.unifr.ch/en/csg/0844/132",
            "width": 100,
            "height": 150,
            "label": "f. 132"
        },
        {
            "id": "243514",
            "src": "https://www.e-codices.unifr.ch/loris/csg/csg-0844/csg-0844_133.jp2/full/,150/0/default/jpg",
            "href": "https://www.e-codices.unifr.ch/en/csg/0844/133",
            "width": 100,
            "height": 150,
            "label": "f. 133"
        },
        {
            "id": "243515",
            "src": "https://www.e-codices.unifr.ch/loris/csg/csg-0844/csg-0844_134.jp2/full/,150/0/default/jpg",
            "href": "https://www.e-codices.unifr.ch/en/csg/0844/134",
            "width": 100,
            "height": 150,
            "label": "f. 134"
        },
        {
            "id": "243516",
            "src": "https://www.e-codices.unifr.ch/loris/csg/csg-0844/csg-0844_135.jp2/full/,150/0/default/jpg",
            "href": "https://www.e-codices.unifr.ch/en/csg/0844/135",
            "width": 100,
            "height": 150,
            "label": "f. 135"
        },
        {
            "id": "243517",
            "src": "https://www.e-codices.unifr.ch/loris/csg/csg-0844/csg-0844_136.jp2/full/,150/0/default/jpg",
            "href": "https://www.e-codices.unifr.ch/en/csg/0844/136",
            "width": 100,
            "height": 150,
            "label": "f. 136"
        },
        {
            "id": "243518",
            "src": "https://www.e-codices.unifr.ch/loris/csg/csg-0844/csg-0844_137.jp2/full/,150/0/default/jpg",
            "href": "https://www.e-codices.unifr.ch/en/csg/0844/137",
            "width": 100,
            "height": 150,
            "label": "f. 137"
        },
        {
            "id": "243519",
            "src": "https://www.e-codices.unifr.ch/loris/csg/csg-0844/csg-0844_138.jp2/full/,150/0/default/jpg",
            "href": "https://www.e-codices.unifr.ch/en/csg/0844/138",
            "width": 100,
            "height": 150,
            "label": "f. 138"
        },
        {
            "id": "243520",
            "src": "https://www.e-codices.unifr.ch/loris/csg/csg-0844/csg-0844_139.jp2/full/,150/0/default/jpg",
            "href": "https://www.e-codices.unifr.ch/en/csg/0844/139",
            "width": 100,
            "height": 150,
            "label": "f. 139"
        },
        {
            "id": "243521",
            "src": "https://www.e-codices.unifr.ch/loris/csg/csg-0844/csg-0844_140.jp2/full/,150/0/default/jpg",
            "href": "https://www.e-codices.unifr.ch/en/csg/0844/140",
            "width": 100,
            "height": 150,
            "label": "f. 140"
        },
        {
            "id": "243522",
            "src": "https://www.e-codices.unifr.ch/loris/csg/csg-0844/csg-0844_141.jp2/full/,150/0/default/jpg",
            "href": "https://www.e-codices.unifr.ch/en/csg/0844/141",
            "width": 100,
            "height": 150,
            "label": "f. 141"
        },
        {
            "id": "243523",
            "src": "https://www.e-codices.unifr.ch/loris/csg/csg-0844/csg-0844_142.jp2/full/,150/0/default/jpg",
            "href": "https://www.e-codices.unifr.ch/en/csg/0844/142",
            "width": 100,
            "height": 150,
            "label": "f. 142"
        },
        {
            "id": "243524",
            "src": "https://www.e-codices.unifr.ch/loris/csg/csg-0844/csg-0844_143.jp2/full/,150/0/default/jpg",
            "href": "https://www.e-codices.unifr.ch/en/csg/0844/143",
            "width": 100,
            "height": 150,
            "label": "f. 143"
        },
        {
            "id": "243525",
            "src": "https://www.e-codices.unifr.ch/loris/csg/csg-0844/csg-0844_144.jp2/full/,150/0/default/jpg",
            "href": "https://www.e-codices.unifr.ch/en/csg/0844/144",
            "width": 100,
            "height": 150,
            "label": "f. 144"
        },
        {
            "id": "243526",
            "src": "https://www.e-codices.unifr.ch/loris/csg/csg-0844/csg-0844_145.jp2/full/,150/0/default/jpg",
            "href": "https://www.e-codices.unifr.ch/en/csg/0844/145",
            "width": 100,
            "height": 150,
            "label": "f. 145"
        },
        {
            "id": "243527",
            "src": "https://www.e-codices.unifr.ch/loris/csg/csg-0844/csg-0844_146.jp2/full/,150/0/default/jpg",
            "href": "https://www.e-codices.unifr.ch/en/csg/0844/146",
            "width": 100,
            "height": 150,
            "label": "f. 146"
        },
        {
            "id": "243528",
            "src": "https://www.e-codices.unifr.ch/loris/csg/csg-0844/csg-0844_147.jp2/full/,150/0/default/jpg",
            "href": "https://www.e-codices.unifr.ch/en/csg/0844/147",
            "width": 100,
            "height": 150,
            "label": "f. 147"
        },
        {
            "id": "243529",
            "src": "https://www.e-codices.unifr.ch/loris/csg/csg-0844/csg-0844_148.jp2/full/,150/0/default/jpg",
            "href": "https://www.e-codices.unifr.ch/en/csg/0844/148",
            "width": 100,
            "height": 150,
            "label": "f. 148"
        },
        {
            "id": "243530",
            "src": "https://www.e-codices.unifr.ch/loris/csg/csg-0844/csg-0844_149.jp2/full/,150/0/default/jpg",
            "href": "https://www.e-codices.unifr.ch/en/csg/0844/149",
            "width": 100,
            "height": 150,
            "label": "f. 149"
        },
        {
            "id": "243531",
            "src": "https://www.e-codices.unifr.ch/loris/csg/csg-0844/csg-0844_150.jp2/full/,150/0/default/jpg",
            "href": "https://www.e-codices.unifr.ch/en/csg/0844/150",
            "width": 100,
            "height": 150,
            "label": "f. 150"
        },
        {
            "id": "243532",
            "src": "https://www.e-codices.unifr.ch/loris/csg/csg-0844/csg-0844_151.jp2/full/,150/0/default/jpg",
            "href": "https://www.e-codices.unifr.ch/en/csg/0844/151",
            "width": 100,
            "height": 150,
            "label": "f. 151"
        },
        {
            "id": "243533",
            "src": "https://www.e-codices.unifr.ch/loris/csg/csg-0844/csg-0844_152.jp2/full/,150/0/default/jpg",
            "href": "https://www.e-codices.unifr.ch/en/csg/0844/152",
            "width": 100,
            "height": 150,
            "label": "f. 152"
        },
        {
            "id": "243534",
            "src": "https://www.e-codices.unifr.ch/loris/csg/csg-0844/csg-0844_153.jp2/full/,150/0/default/jpg",
            "href": "https://www.e-codices.unifr.ch/en/csg/0844/153",
            "width": 100,
            "height": 150,
            "label": "f. 153"
        },
        {
            "id": "243535",
            "src": "https://www.e-codices.unifr.ch/loris/csg/csg-0844/csg-0844_154.jp2/full/,150/0/default/jpg",
            "href": "https://www.e-codices.unifr.ch/en/csg/0844/154",
            "width": 100,
            "height": 150,
            "label": "f. 154"
        },
        {
            "id": "243536",
            "src": "https://www.e-codices.unifr.ch/loris/csg/csg-0844/csg-0844_155.jp2/full/,150/0/default/jpg",
            "href": "https://www.e-codices.unifr.ch/en/csg/0844/155",
            "width": 100,
            "height": 150,
            "label": "f. 155"
        },
        {
            "id": "243537",
            "src": "https://www.e-codices.unifr.ch/loris/csg/csg-0844/csg-0844_156.jp2/full/,150/0/default/jpg",
            "href": "https://www.e-codices.unifr.ch/en/csg/0844/156",
            "width": 100,
            "height": 150,
            "label": "f. 156"
        },
        {
            "id": "243538",
            "src": "https://www.e-codices.unifr.ch/loris/csg/csg-0844/csg-0844_157.jp2/full/,150/0/default/jpg",
            "href": "https://www.e-codices.unifr.ch/en/csg/0844/157",
            "width": 100,
            "height": 150,
            "label": "f. 157"
        },
        {
            "id": "243539",
            "src": "https://www.e-codices.unifr.ch/loris/csg/csg-0844/csg-0844_158.jp2/full/,150/0/default/jpg",
            "href": "https://www.e-codices.unifr.ch/en/csg/0844/158",
            "width": 100,
            "height": 150,
            "label": "f. 158"
        },
        {
            "id": "243540",
            "src": "https://www.e-codices.unifr.ch/loris/csg/csg-0844/csg-0844_159.jp2/full/,150/0/default/jpg",
            "href": "https://www.e-codices.unifr.ch/en/csg/0844/159",
            "width": 100,
            "height": 150,
            "label": "f. 159"
        },
        {
            "id": "243541",
            "src": "https://www.e-codices.unifr.ch/loris/csg/csg-0844/csg-0844_160.jp2/full/,150/0/default/jpg",
            "href": "https://www.e-codices.unifr.ch/en/csg/0844/160",
            "width": 100,
            "height": 150,
            "label": "f. 160"
        },
        {
            "id": "243542",
            "src": "https://www.e-codices.unifr.ch/loris/csg/csg-0844/csg-0844_161.jp2/full/,150/0/default/jpg",
            "href": "https://www.e-codices.unifr.ch/en/csg/0844/161",
            "width": 100,
            "height": 150,
            "label": "f. 161"
        },
        {
            "id": "243543",
            "src": "https://www.e-codices.unifr.ch/loris/csg/csg-0844/csg-0844_162.jp2/full/,150/0/default/jpg",
            "href": "https://www.e-codices.unifr.ch/en/csg/0844/162",
            "width": 100,
            "height": 150,
            "label": "f. 162"
        },
        {
            "id": "243544",
            "src": "https://www.e-codices.unifr.ch/loris/csg/csg-0844/csg-0844_163.jp2/full/,150/0/default/jpg",
            "href": "https://www.e-codices.unifr.ch/en/csg/0844/163",
            "width": 100,
            "height": 150,
            "label": "f. 163"
        },
        {
            "id": "243545",
            "src": "https://www.e-codices.unifr.ch/loris/csg/csg-0844/csg-0844_164.jp2/full/,150/0/default/jpg",
            "href": "https://www.e-codices.unifr.ch/en/csg/0844/164",
            "width": 100,
            "height": 150,
            "label": "f. 164"
        },
        {
            "id": "243546",
            "src": "https://www.e-codices.unifr.ch/loris/csg/csg-0844/csg-0844_165.jp2/full/,150/0/default/jpg",
            "href": "https://www.e-codices.unifr.ch/en/csg/0844/165",
            "width": 100,
            "height": 150,
            "label": "f. 165"
        },
        {
            "id": "243547",
            "src": "https://www.e-codices.unifr.ch/loris/csg/csg-0844/csg-0844_166.jp2/full/,150/0/default/jpg",
            "href": "https://www.e-codices.unifr.ch/en/csg/0844/166",
            "width": 100,
            "height": 150,
            "label": "f. 166"
        },
        {
            "id": "243548",
            "src": "https://www.e-codices.unifr.ch/loris/csg/csg-0844/csg-0844_167.jp2/full/,150/0/default/jpg",
            "href": "https://www.e-codices.unifr.ch/en/csg/0844/167",
            "width": 100,
            "height": 150,
            "label": "f. 167"
        },
        {
            "id": "243549",
            "src": "https://www.e-codices.unifr.ch/loris/csg/csg-0844/csg-0844_168.jp2/full/,150/0/default/jpg",
            "href": "https://www.e-codices.unifr.ch/en/csg/0844/168",
            "width": 100,
            "height": 150,
            "label": "f. 168"
        },
        {
            "id": "243550",
            "src": "https://www.e-codices.unifr.ch/loris/csg/csg-0844/csg-0844_169.jp2/full/,150/0/default/jpg",
            "href": "https://www.e-codices.unifr.ch/en/csg/0844/169",
            "width": 100,
            "height": 150,
            "label": "f. 169"
        },
        {
            "id": "243551",
            "src": "https://www.e-codices.unifr.ch/loris/csg/csg-0844/csg-0844_170.jp2/full/,150/0/default/jpg",
            "href": "https://www.e-codices.unifr.ch/en/csg/0844/170",
            "width": 100,
            "height": 150,
            "label": "f. 170"
        },
        {
            "id": "243552",
            "src": "https://www.e-codices.unifr.ch/loris/csg/csg-0844/csg-0844_171.jp2/full/,150/0/default/jpg",
            "href": "https://www.e-codices.unifr.ch/en/csg/0844/171",
            "width": 100,
            "height": 150,
            "label": "f. 171"
        },
        {
            "id": "243553",
            "src": "https://www.e-codices.unifr.ch/loris/csg/csg-0844/csg-0844_172.jp2/full/,150/0/default/jpg",
            "href": "https://www.e-codices.unifr.ch/en/csg/0844/172",
            "width": 100,
            "height": 150,
            "label": "f. 172"
        },
        {
            "id": "243554",
            "src": "https://www.e-codices.unifr.ch/loris/csg/csg-0844/csg-0844_173.jp2/full/,150/0/default/jpg",
            "href": "https://www.e-codices.unifr.ch/en/csg/0844/173",
            "width": 100,
            "height": 150,
            "label": "f. 173"
        },
        {
            "id": "243555",
            "src": "https://www.e-codices.unifr.ch/loris/csg/csg-0844/csg-0844_174.jp2/full/,150/0/default/jpg",
            "href": "https://www.e-codices.unifr.ch/en/csg/0844/174",
            "width": 100,
            "height": 150,
            "label": "f. 174"
        },
        {
            "id": "243556",
            "src": "https://www.e-codices.unifr.ch/loris/csg/csg-0844/csg-0844_175.jp2/full/,150/0/default/jpg",
            "href": "https://www.e-codices.unifr.ch/en/csg/0844/175",
            "width": 100,
            "height": 150,
            "label": "f. 175"
        },
        {
            "id": "243557",
            "src": "https://www.e-codices.unifr.ch/loris/csg/csg-0844/csg-0844_176.jp2/full/,150/0/default/jpg",
            "href": "https://www.e-codices.unifr.ch/en/csg/0844/176",
            "width": 100,
            "height": 150,
            "label": "f. 176"
        },
        {
            "id": "243558",
            "src": "https://www.e-codices.unifr.ch/loris/csg/csg-0844/csg-0844_177.jp2/full/,150/0/default/jpg",
            "href": "https://www.e-codices.unifr.ch/en/csg/0844/177",
            "width": 100,
            "height": 150,
            "label": "f. 177"
        },
        {
            "id": "243559",
            "src": "https://www.e-codices.unifr.ch/loris/csg/csg-0844/csg-0844_178.jp2/full/,150/0/default/jpg",
            "href": "https://www.e-codices.unifr.ch/en/csg/0844/178",
            "width": 100,
            "height": 150,
            "label": "f. 178"
        },
        {
            "id": "243560",
            "src": "https://www.e-codices.unifr.ch/loris/csg/csg-0844/csg-0844_179.jp2/full/,150/0/default/jpg",
            "href": "https://www.e-codices.unifr.ch/en/csg/0844/179",
            "width": 100,
            "height": 150,
            "label": "f. 179"
        },
        {
            "id": "243561",
            "src": "https://www.e-codices.unifr.ch/loris/csg/csg-0844/csg-0844_180.jp2/full/,150/0/default/jpg",
            "href": "https://www.e-codices.unifr.ch/en/csg/0844/180",
            "width": 100,
            "height": 150,
            "label": "f. 180"
        },
        {
            "id": "243562",
            "src": "https://www.e-codices.unifr.ch/loris/csg/csg-0844/csg-0844_181.jp2/full/,150/0/default/jpg",
            "href": "https://www.e-codices.unifr.ch/en/csg/0844/181",
            "width": 100,
            "height": 150,
            "label": "f. 181"
        },
        {
            "id": "243563",
            "src": "https://www.e-codices.unifr.ch/loris/csg/csg-0844/csg-0844_182.jp2/full/,150/0/default/jpg",
            "href": "https://www.e-codices.unifr.ch/en/csg/0844/182",
            "width": 100,
            "height": 150,
            "label": "f. 182"
        },
        {
            "id": "243564",
            "src": "https://www.e-codices.unifr.ch/loris/csg/csg-0844/csg-0844_183.jp2/full/,150/0/default/jpg",
            "href": "https://www.e-codices.unifr.ch/en/csg/0844/183",
            "width": 100,
            "height": 150,
            "label": "f. 183"
        },
        {
            "id": "243565",
            "src": "https://www.e-codices.unifr.ch/loris/csg/csg-0844/csg-0844_184.jp2/full/,150/0/default/jpg",
            "href": "https://www.e-codices.unifr.ch/en/csg/0844/184",
            "width": 100,
            "height": 150,
            "label": "f. 184"
        },
        {
            "id": "243566",
            "src": "https://www.e-codices.unifr.ch/loris/csg/csg-0844/csg-0844_185.jp2/full/,150/0/default/jpg",
            "href": "https://www.e-codices.unifr.ch/en/csg/0844/185",
            "width": 100,
            "height": 150,
            "label": "f. 185"
        },
        {
            "id": "243567",
            "src": "https://www.e-codices.unifr.ch/loris/csg/csg-0844/csg-0844_186.jp2/full/,150/0/default/jpg",
            "href": "https://www.e-codices.unifr.ch/en/csg/0844/186",
            "width": 100,
            "height": 150,
            "label": "f. 186"
        },
        {
            "id": "243573",
            "src": "https://www.e-codices.unifr.ch/loris/csg/csg-0844/csg-0844_e006.jp2/full/,150/0/default/jpg",
            "href": "https://www.e-codices.unifr.ch/en/csg/0844/bindingF",
            "width": 100,
            "height": 150,
            "label": "Rear paste-down"
        },
        {
            "id": "243570",
            "src": "https://www.e-codices.unifr.ch/loris/csg/csg-0844/csg-0844_e003.jp2/full/,150/0/default/jpg",
            "href": "https://www.e-codices.unifr.ch/en/csg/0844/bindingC",
            "width": 100,
            "height": 150,
            "label": "Back cover"
        },
        {
            "id": "243569",
            "src": "https://www.e-codices.unifr.ch/loris/csg/csg-0844/csg-0844_e002.jp2/full/,150/0/default/jpg",
            "href": "https://www.e-codices.unifr.ch/en/csg/0844/bindingB",
            "width": 100,
            "height": 150,
            "label": "Spine"
        },
        {
            "id": "243571",
            "src": "https://www.e-codices.unifr.ch/loris/csg/csg-0844/csg-0844_e004.jp2/full/,150/0/default/jpg",
            "href": "https://www.e-codices.unifr.ch/en/csg/0844/bindingD",
            "width": 100,
            "height": 150,
            "label": "Fore edge"
        },
        {
            "id": "243574",
            "src": "https://www.e-codices.unifr.ch/loris/csg/csg-0844/csg-0844_e007.jp2/full/,150/0/default/jpg",
            "href": "https://www.e-codices.unifr.ch/en/csg/0844/bindingG",
            "width": 100,
            "height": 150,
            "label": "Head"
        },
        {
            "id": "243575",
            "src": "https://www.e-codices.unifr.ch/loris/csg/csg-0844/csg-0844_e008.jp2/full/,150/0/default/jpg",
            "href": "https://www.e-codices.unifr.ch/en/csg/0844/bindingH",
            "width": 100,
            "height": 150,
            "label": "Tail"
        },
        {
            "id": "243576",
            "src": "https://www.e-codices.unifr.ch/loris/csg/csg-0844/csg-0844_Mass.jp2/full/,150/0/default/jpg",
            "href": "https://www.e-codices.unifr.ch/en/csg/0844/bindingRuler",
            "width": 100,
            "height": 150,
            "label": "Ruler"
        },
        {
            "id": "243577",
            "src": "https://www.e-codices.unifr.ch/loris/csg/csg-0844/csg-0844_Profil.jp2/full/,150/0/default/jpg",
            "href": "https://www.e-codices.unifr.ch/en/csg/0844/bindingProfile",
            "width": 100,
            "height": 150,
            "label": "Color profile"
        },
        {
            "id": "243578",
            "src": "https://www.e-codices.unifr.ch/loris/csg/csg-0844/csg-0844_Profil1.jp2/full/,150/0/default/jpg",
            "href": "https://www.e-codices.unifr.ch/en/csg/0844/bindingProfile",
            "width": 100,
            "height": 150,
            "label": "Color profile"
        }
    ],
    "customViewerBackgroundColor": "#000000"
}